package com.google.android.gms.ads.internal.client;

import android.os.Binder;
import android.os.IBinder;
import android.os.IInterface;
import android.os.Parcel;
import android.os.RemoteException;
import com.google.android.gms.dynamic.zzd;
import com.google.android.gms.dynamic.zzd.zza;
import com.google.android.gms.internal.zzcl;
import com.google.android.gms.internal.zzcl.zza;
import com.google.android.gms.internal.zzgc;
import com.google.android.gms.internal.zzgc.zza;
import com.google.android.gms.internal.zzgg;
import com.google.android.gms.internal.zzgg.zza;

public abstract interface zzs
  extends IInterface
{
  public abstract void destroy()
    throws RemoteException;
  
  public abstract String getMediationAdapterClassName()
    throws RemoteException;
  
  public abstract boolean isLoading()
    throws RemoteException;
  
  public abstract boolean isReady()
    throws RemoteException;
  
  public abstract void pause()
    throws RemoteException;
  
  public abstract void resume()
    throws RemoteException;
  
  public abstract void setManualImpressionsEnabled(boolean paramBoolean)
    throws RemoteException;
  
  public abstract void showInterstitial()
    throws RemoteException;
  
  public abstract void stopLoading()
    throws RemoteException;
  
  public abstract void zza(AdSizeParcel paramAdSizeParcel)
    throws RemoteException;
  
  public abstract void zza(zzn paramzzn)
    throws RemoteException;
  
  public abstract void zza(zzo paramzzo)
    throws RemoteException;
  
  public abstract void zza(zzu paramzzu)
    throws RemoteException;
  
  public abstract void zza(zzv paramzzv)
    throws RemoteException;
  
  public abstract void zza(zzcl paramzzcl)
    throws RemoteException;
  
  public abstract void zza(zzgc paramzzgc)
    throws RemoteException;
  
  public abstract void zza(zzgg paramzzgg, String paramString)
    throws RemoteException;
  
  public abstract zzd zzaO()
    throws RemoteException;
  
  public abstract AdSizeParcel zzaP()
    throws RemoteException;
  
  public abstract void zzaR()
    throws RemoteException;
  
  public abstract boolean zzb(AdRequestParcel paramAdRequestParcel)
    throws RemoteException;
  
  public static abstract class zza
    extends Binder
    implements zzs
  {
    public zza()
    {
      attachInterface(this, "com.google.android.gms.ads.internal.client.IAdManager");
    }
    
    public static zzs zzk(IBinder paramIBinder)
    {
      if (paramIBinder == null) {
        return null;
      }
      IInterface localIInterface = paramIBinder.queryLocalInterface("com.google.android.gms.ads.internal.client.IAdManager");
      if ((localIInterface != null) && ((localIInterface instanceof zzs))) {
        return (zzs)localIInterface;
      }
      return new zza(paramIBinder);
    }
    
    public IBinder asBinder()
    {
      return this;
    }
    
    public boolean onTransact(int paramInt1, Parcel paramParcel1, Parcel paramParcel2, int paramInt2)
      throws RemoteException
    {
      switch (paramInt1)
      {
      default: 
        return super.onTransact(paramInt1, paramParcel1, paramParcel2, paramInt2);
      case 1598968902: 
        paramParcel2.writeString("com.google.android.gms.ads.internal.client.IAdManager");
        return true;
      case 1: 
        paramParcel1.enforceInterface("com.google.android.gms.ads.internal.client.IAdManager");
        zzd localzzd = zzaO();
        paramParcel2.writeNoException();
        IBinder localIBinder = null;
        if (localzzd != null) {
          localIBinder = localzzd.asBinder();
        }
        paramParcel2.writeStrongBinder(localIBinder);
        return true;
      case 2: 
        paramParcel1.enforceInterface("com.google.android.gms.ads.internal.client.IAdManager");
        destroy();
        paramParcel2.writeNoException();
        return true;
      case 3: 
        paramParcel1.enforceInterface("com.google.android.gms.ads.internal.client.IAdManager");
        boolean bool4 = isReady();
        paramParcel2.writeNoException();
        if (bool4) {}
        for (int i1 = 1;; i1 = 0)
        {
          paramParcel2.writeInt(i1);
          return true;
        }
      case 4: 
        paramParcel1.enforceInterface("com.google.android.gms.ads.internal.client.IAdManager");
        int m = paramParcel1.readInt();
        AdRequestParcel localAdRequestParcel = null;
        if (m != 0) {
          localAdRequestParcel = AdRequestParcel.CREATOR.zzb(paramParcel1);
        }
        boolean bool3 = zzb(localAdRequestParcel);
        paramParcel2.writeNoException();
        int n = 0;
        if (bool3) {
          n = 1;
        }
        paramParcel2.writeInt(n);
        return true;
      case 5: 
        paramParcel1.enforceInterface("com.google.android.gms.ads.internal.client.IAdManager");
        pause();
        paramParcel2.writeNoException();
        return true;
      case 6: 
        paramParcel1.enforceInterface("com.google.android.gms.ads.internal.client.IAdManager");
        resume();
        paramParcel2.writeNoException();
        return true;
      case 7: 
        paramParcel1.enforceInterface("com.google.android.gms.ads.internal.client.IAdManager");
        zza(zzo.zza.zzg(paramParcel1.readStrongBinder()));
        paramParcel2.writeNoException();
        return true;
      case 8: 
        paramParcel1.enforceInterface("com.google.android.gms.ads.internal.client.IAdManager");
        zza(zzu.zza.zzm(paramParcel1.readStrongBinder()));
        paramParcel2.writeNoException();
        return true;
      case 9: 
        paramParcel1.enforceInterface("com.google.android.gms.ads.internal.client.IAdManager");
        showInterstitial();
        paramParcel2.writeNoException();
        return true;
      case 10: 
        paramParcel1.enforceInterface("com.google.android.gms.ads.internal.client.IAdManager");
        stopLoading();
        paramParcel2.writeNoException();
        return true;
      case 11: 
        paramParcel1.enforceInterface("com.google.android.gms.ads.internal.client.IAdManager");
        zzaR();
        paramParcel2.writeNoException();
        return true;
      case 12: 
        paramParcel1.enforceInterface("com.google.android.gms.ads.internal.client.IAdManager");
        AdSizeParcel localAdSizeParcel2 = zzaP();
        paramParcel2.writeNoException();
        if (localAdSizeParcel2 != null)
        {
          paramParcel2.writeInt(1);
          localAdSizeParcel2.writeToParcel(paramParcel2, 1);
          return true;
        }
        paramParcel2.writeInt(0);
        return true;
      case 13: 
        paramParcel1.enforceInterface("com.google.android.gms.ads.internal.client.IAdManager");
        int k = paramParcel1.readInt();
        AdSizeParcel localAdSizeParcel1 = null;
        if (k != 0) {
          localAdSizeParcel1 = AdSizeParcel.CREATOR.zzc(paramParcel1);
        }
        zza(localAdSizeParcel1);
        paramParcel2.writeNoException();
        return true;
      case 14: 
        paramParcel1.enforceInterface("com.google.android.gms.ads.internal.client.IAdManager");
        zza(zzgc.zza.zzP(paramParcel1.readStrongBinder()));
        paramParcel2.writeNoException();
        return true;
      case 15: 
        paramParcel1.enforceInterface("com.google.android.gms.ads.internal.client.IAdManager");
        zza(zzgg.zza.zzT(paramParcel1.readStrongBinder()), paramParcel1.readString());
        paramParcel2.writeNoException();
        return true;
      case 18: 
        paramParcel1.enforceInterface("com.google.android.gms.ads.internal.client.IAdManager");
        String str = getMediationAdapterClassName();
        paramParcel2.writeNoException();
        paramParcel2.writeString(str);
        return true;
      case 19: 
        paramParcel1.enforceInterface("com.google.android.gms.ads.internal.client.IAdManager");
        zza(zzcl.zza.zzs(paramParcel1.readStrongBinder()));
        paramParcel2.writeNoException();
        return true;
      case 20: 
        paramParcel1.enforceInterface("com.google.android.gms.ads.internal.client.IAdManager");
        zza(zzn.zza.zzf(paramParcel1.readStrongBinder()));
        paramParcel2.writeNoException();
        return true;
      case 21: 
        paramParcel1.enforceInterface("com.google.android.gms.ads.internal.client.IAdManager");
        zza(zzv.zza.zzn(paramParcel1.readStrongBinder()));
        paramParcel2.writeNoException();
        return true;
      case 22: 
        paramParcel1.enforceInterface("com.google.android.gms.ads.internal.client.IAdManager");
        int j = paramParcel1.readInt();
        boolean bool2 = false;
        if (j != 0) {
          bool2 = true;
        }
        setManualImpressionsEnabled(bool2);
        paramParcel2.writeNoException();
        return true;
      }
      paramParcel1.enforceInterface("com.google.android.gms.ads.internal.client.IAdManager");
      boolean bool1 = isLoading();
      paramParcel2.writeNoException();
      int i = 0;
      if (bool1) {
        i = 1;
      }
      paramParcel2.writeInt(i);
      return true;
    }
    
    private static class zza
      implements zzs
    {
      private IBinder zzoo;
      
      zza(IBinder paramIBinder)
      {
        this.zzoo = paramIBinder;
      }
      
      public IBinder asBinder()
      {
        return this.zzoo;
      }
      
      public void destroy()
        throws RemoteException
      {
        Parcel localParcel1 = Parcel.obtain();
        Parcel localParcel2 = Parcel.obtain();
        try
        {
          localParcel1.writeInterfaceToken("com.google.android.gms.ads.internal.client.IAdManager");
          this.zzoo.transact(2, localParcel1, localParcel2, 0);
          localParcel2.readException();
          return;
        }
        finally
        {
          localParcel2.recycle();
          localParcel1.recycle();
        }
      }
      
      public String getMediationAdapterClassName()
        throws RemoteException
      {
        Parcel localParcel1 = Parcel.obtain();
        Parcel localParcel2 = Parcel.obtain();
        try
        {
          localParcel1.writeInterfaceToken("com.google.android.gms.ads.internal.client.IAdManager");
          this.zzoo.transact(18, localParcel1, localParcel2, 0);
          localParcel2.readException();
          String str = localParcel2.readString();
          return str;
        }
        finally
        {
          localParcel2.recycle();
          localParcel1.recycle();
        }
      }
      
      public boolean isLoading()
        throws RemoteException
      {
        Parcel localParcel1 = Parcel.obtain();
        Parcel localParcel2 = Parcel.obtain();
        try
        {
          localParcel1.writeInterfaceToken("com.google.android.gms.ads.internal.client.IAdManager");
          this.zzoo.transact(23, localParcel1, localParcel2, 0);
          localParcel2.readException();
          int i = localParcel2.readInt();
          boolean bool = false;
          if (i != 0) {
            bool = true;
          }
          return bool;
        }
        finally
        {
          localParcel2.recycle();
          localParcel1.recycle();
        }
      }
      
      public boolean isReady()
        throws RemoteException
      {
        Parcel localParcel1 = Parcel.obtain();
        Parcel localParcel2 = Parcel.obtain();
        try
        {
          localParcel1.writeInterfaceToken("com.google.android.gms.ads.internal.client.IAdManager");
          this.zzoo.transact(3, localParcel1, localParcel2, 0);
          localParcel2.readException();
          int i = localParcel2.readInt();
          boolean bool = false;
          if (i != 0) {
            bool = true;
          }
          return bool;
        }
        finally
        {
          localParcel2.recycle();
          localParcel1.recycle();
        }
      }
      
      public void pause()
        throws RemoteException
      {
        Parcel localParcel1 = Parcel.obtain();
        Parcel localParcel2 = Parcel.obtain();
        try
        {
          localParcel1.writeInterfaceToken("com.google.android.gms.ads.internal.client.IAdManager");
          this.zzoo.transact(5, localParcel1, localParcel2, 0);
          localParcel2.readException();
          return;
        }
        finally
        {
          localParcel2.recycle();
          localParcel1.recycle();
        }
      }
      
      public void resume()
        throws RemoteException
      {
        Parcel localParcel1 = Parcel.obtain();
        Parcel localParcel2 = Parcel.obtain();
        try
        {
          localParcel1.writeInterfaceToken("com.google.android.gms.ads.internal.client.IAdManager");
          this.zzoo.transact(6, localParcel1, localParcel2, 0);
          localParcel2.readException();
          return;
        }
        finally
        {
          localParcel2.recycle();
          localParcel1.recycle();
        }
      }
      
      public void setManualImpressionsEnabled(boolean paramBoolean)
        throws RemoteException
      {
        Parcel localParcel1 = Parcel.obtain();
        Parcel localParcel2 = Parcel.obtain();
        try
        {
          localParcel1.writeInterfaceToken("com.google.android.gms.ads.internal.client.IAdManager");
          int i = 0;
          if (paramBoolean) {
            i = 1;
          }
          localParcel1.writeInt(i);
          this.zzoo.transact(22, localParcel1, localParcel2, 0);
          localParcel2.readException();
          return;
        }
        finally
        {
          localParcel2.recycle();
          localParcel1.recycle();
        }
      }
      
      public void showInterstitial()
        throws RemoteException
      {
        Parcel localParcel1 = Parcel.obtain();
        Parcel localParcel2 = Parcel.obtain();
        try
        {
          localParcel1.writeInterfaceToken("com.google.android.gms.ads.internal.client.IAdManager");
          this.zzoo.transact(9, localParcel1, localParcel2, 0);
          localParcel2.readException();
          return;
        }
        finally
        {
          localParcel2.recycle();
          localParcel1.recycle();
        }
      }
      
      public void stopLoading()
        throws RemoteException
      {
        Parcel localParcel1 = Parcel.obtain();
        Parcel localParcel2 = Parcel.obtain();
        try
        {
          localParcel1.writeInterfaceToken("com.google.android.gms.ads.internal.client.IAdManager");
          this.zzoo.transact(10, localParcel1, localParcel2, 0);
          localParcel2.readException();
          return;
        }
        finally
        {
          localParcel2.recycle();
          localParcel1.recycle();
        }
      }
      
      /* Error */
      public void zza(AdSizeParcel paramAdSizeParcel)
        throws RemoteException
      {
        // Byte code:
        //   0: invokestatic 26	android/os/Parcel:obtain	()Landroid/os/Parcel;
        //   3: astore_2
        //   4: invokestatic 26	android/os/Parcel:obtain	()Landroid/os/Parcel;
        //   7: astore_3
        //   8: aload_2
        //   9: ldc 28
        //   11: invokevirtual 32	android/os/Parcel:writeInterfaceToken	(Ljava/lang/String;)V
        //   14: aload_1
        //   15: ifnull +42 -> 57
        //   18: aload_2
        //   19: iconst_1
        //   20: invokevirtual 64	android/os/Parcel:writeInt	(I)V
        //   23: aload_1
        //   24: aload_2
        //   25: iconst_0
        //   26: invokevirtual 74	com/google/android/gms/ads/internal/client/AdSizeParcel:writeToParcel	(Landroid/os/Parcel;I)V
        //   29: aload_0
        //   30: getfield 15	com/google/android/gms/ads/internal/client/zzs$zza$zza:zzoo	Landroid/os/IBinder;
        //   33: bipush 13
        //   35: aload_2
        //   36: aload_3
        //   37: iconst_0
        //   38: invokeinterface 38 5 0
        //   43: pop
        //   44: aload_3
        //   45: invokevirtual 41	android/os/Parcel:readException	()V
        //   48: aload_3
        //   49: invokevirtual 44	android/os/Parcel:recycle	()V
        //   52: aload_2
        //   53: invokevirtual 44	android/os/Parcel:recycle	()V
        //   56: return
        //   57: aload_2
        //   58: iconst_0
        //   59: invokevirtual 64	android/os/Parcel:writeInt	(I)V
        //   62: goto -33 -> 29
        //   65: astore 4
        //   67: aload_3
        //   68: invokevirtual 44	android/os/Parcel:recycle	()V
        //   71: aload_2
        //   72: invokevirtual 44	android/os/Parcel:recycle	()V
        //   75: aload 4
        //   77: athrow
        // Local variable table:
        //   start	length	slot	name	signature
        //   0	78	0	this	zza
        //   0	78	1	paramAdSizeParcel	AdSizeParcel
        //   3	69	2	localParcel1	Parcel
        //   7	61	3	localParcel2	Parcel
        //   65	11	4	localObject	Object
        // Exception table:
        //   from	to	target	type
        //   8	14	65	finally
        //   18	29	65	finally
        //   29	48	65	finally
        //   57	62	65	finally
      }
      
      /* Error */
      public void zza(zzn paramzzn)
        throws RemoteException
      {
        // Byte code:
        //   0: invokestatic 26	android/os/Parcel:obtain	()Landroid/os/Parcel;
        //   3: astore_2
        //   4: invokestatic 26	android/os/Parcel:obtain	()Landroid/os/Parcel;
        //   7: astore_3
        //   8: aload_2
        //   9: ldc 28
        //   11: invokevirtual 32	android/os/Parcel:writeInterfaceToken	(Ljava/lang/String;)V
        //   14: aload_1
        //   15: ifnull +45 -> 60
        //   18: aload_1
        //   19: invokeinterface 79 1 0
        //   24: astore 5
        //   26: aload_2
        //   27: aload 5
        //   29: invokevirtual 82	android/os/Parcel:writeStrongBinder	(Landroid/os/IBinder;)V
        //   32: aload_0
        //   33: getfield 15	com/google/android/gms/ads/internal/client/zzs$zza$zza:zzoo	Landroid/os/IBinder;
        //   36: bipush 20
        //   38: aload_2
        //   39: aload_3
        //   40: iconst_0
        //   41: invokeinterface 38 5 0
        //   46: pop
        //   47: aload_3
        //   48: invokevirtual 41	android/os/Parcel:readException	()V
        //   51: aload_3
        //   52: invokevirtual 44	android/os/Parcel:recycle	()V
        //   55: aload_2
        //   56: invokevirtual 44	android/os/Parcel:recycle	()V
        //   59: return
        //   60: aconst_null
        //   61: astore 5
        //   63: goto -37 -> 26
        //   66: astore 4
        //   68: aload_3
        //   69: invokevirtual 44	android/os/Parcel:recycle	()V
        //   72: aload_2
        //   73: invokevirtual 44	android/os/Parcel:recycle	()V
        //   76: aload 4
        //   78: athrow
        // Local variable table:
        //   start	length	slot	name	signature
        //   0	79	0	this	zza
        //   0	79	1	paramzzn	zzn
        //   3	70	2	localParcel1	Parcel
        //   7	62	3	localParcel2	Parcel
        //   66	11	4	localObject	Object
        //   24	38	5	localIBinder	IBinder
        // Exception table:
        //   from	to	target	type
        //   8	14	66	finally
        //   18	26	66	finally
        //   26	51	66	finally
      }
      
      /* Error */
      public void zza(zzo paramzzo)
        throws RemoteException
      {
        // Byte code:
        //   0: invokestatic 26	android/os/Parcel:obtain	()Landroid/os/Parcel;
        //   3: astore_2
        //   4: invokestatic 26	android/os/Parcel:obtain	()Landroid/os/Parcel;
        //   7: astore_3
        //   8: aload_2
        //   9: ldc 28
        //   11: invokevirtual 32	android/os/Parcel:writeInterfaceToken	(Ljava/lang/String;)V
        //   14: aload_1
        //   15: ifnull +45 -> 60
        //   18: aload_1
        //   19: invokeinterface 86 1 0
        //   24: astore 5
        //   26: aload_2
        //   27: aload 5
        //   29: invokevirtual 82	android/os/Parcel:writeStrongBinder	(Landroid/os/IBinder;)V
        //   32: aload_0
        //   33: getfield 15	com/google/android/gms/ads/internal/client/zzs$zza$zza:zzoo	Landroid/os/IBinder;
        //   36: bipush 7
        //   38: aload_2
        //   39: aload_3
        //   40: iconst_0
        //   41: invokeinterface 38 5 0
        //   46: pop
        //   47: aload_3
        //   48: invokevirtual 41	android/os/Parcel:readException	()V
        //   51: aload_3
        //   52: invokevirtual 44	android/os/Parcel:recycle	()V
        //   55: aload_2
        //   56: invokevirtual 44	android/os/Parcel:recycle	()V
        //   59: return
        //   60: aconst_null
        //   61: astore 5
        //   63: goto -37 -> 26
        //   66: astore 4
        //   68: aload_3
        //   69: invokevirtual 44	android/os/Parcel:recycle	()V
        //   72: aload_2
        //   73: invokevirtual 44	android/os/Parcel:recycle	()V
        //   76: aload 4
        //   78: athrow
        // Local variable table:
        //   start	length	slot	name	signature
        //   0	79	0	this	zza
        //   0	79	1	paramzzo	zzo
        //   3	70	2	localParcel1	Parcel
        //   7	62	3	localParcel2	Parcel
        //   66	11	4	localObject	Object
        //   24	38	5	localIBinder	IBinder
        // Exception table:
        //   from	to	target	type
        //   8	14	66	finally
        //   18	26	66	finally
        //   26	51	66	finally
      }
      
      /* Error */
      public void zza(zzu paramzzu)
        throws RemoteException
      {
        // Byte code:
        //   0: invokestatic 26	android/os/Parcel:obtain	()Landroid/os/Parcel;
        //   3: astore_2
        //   4: invokestatic 26	android/os/Parcel:obtain	()Landroid/os/Parcel;
        //   7: astore_3
        //   8: aload_2
        //   9: ldc 28
        //   11: invokevirtual 32	android/os/Parcel:writeInterfaceToken	(Ljava/lang/String;)V
        //   14: aload_1
        //   15: ifnull +45 -> 60
        //   18: aload_1
        //   19: invokeinterface 90 1 0
        //   24: astore 5
        //   26: aload_2
        //   27: aload 5
        //   29: invokevirtual 82	android/os/Parcel:writeStrongBinder	(Landroid/os/IBinder;)V
        //   32: aload_0
        //   33: getfield 15	com/google/android/gms/ads/internal/client/zzs$zza$zza:zzoo	Landroid/os/IBinder;
        //   36: bipush 8
        //   38: aload_2
        //   39: aload_3
        //   40: iconst_0
        //   41: invokeinterface 38 5 0
        //   46: pop
        //   47: aload_3
        //   48: invokevirtual 41	android/os/Parcel:readException	()V
        //   51: aload_3
        //   52: invokevirtual 44	android/os/Parcel:recycle	()V
        //   55: aload_2
        //   56: invokevirtual 44	android/os/Parcel:recycle	()V
        //   59: return
        //   60: aconst_null
        //   61: astore 5
        //   63: goto -37 -> 26
        //   66: astore 4
        //   68: aload_3
        //   69: invokevirtual 44	android/os/Parcel:recycle	()V
        //   72: aload_2
        //   73: invokevirtual 44	android/os/Parcel:recycle	()V
        //   76: aload 4
        //   78: athrow
        // Local variable table:
        //   start	length	slot	name	signature
        //   0	79	0	this	zza
        //   0	79	1	paramzzu	zzu
        //   3	70	2	localParcel1	Parcel
        //   7	62	3	localParcel2	Parcel
        //   66	11	4	localObject	Object
        //   24	38	5	localIBinder	IBinder
        // Exception table:
        //   from	to	target	type
        //   8	14	66	finally
        //   18	26	66	finally
        //   26	51	66	finally
      }
      
      /* Error */
      public void zza(zzv paramzzv)
        throws RemoteException
      {
        // Byte code:
        //   0: invokestatic 26	android/os/Parcel:obtain	()Landroid/os/Parcel;
        //   3: astore_2
        //   4: invokestatic 26	android/os/Parcel:obtain	()Landroid/os/Parcel;
        //   7: astore_3
        //   8: aload_2
        //   9: ldc 28
        //   11: invokevirtual 32	android/os/Parcel:writeInterfaceToken	(Ljava/lang/String;)V
        //   14: aload_1
        //   15: ifnull +45 -> 60
        //   18: aload_1
        //   19: invokeinterface 94 1 0
        //   24: astore 5
        //   26: aload_2
        //   27: aload 5
        //   29: invokevirtual 82	android/os/Parcel:writeStrongBinder	(Landroid/os/IBinder;)V
        //   32: aload_0
        //   33: getfield 15	com/google/android/gms/ads/internal/client/zzs$zza$zza:zzoo	Landroid/os/IBinder;
        //   36: bipush 21
        //   38: aload_2
        //   39: aload_3
        //   40: iconst_0
        //   41: invokeinterface 38 5 0
        //   46: pop
        //   47: aload_3
        //   48: invokevirtual 41	android/os/Parcel:readException	()V
        //   51: aload_3
        //   52: invokevirtual 44	android/os/Parcel:recycle	()V
        //   55: aload_2
        //   56: invokevirtual 44	android/os/Parcel:recycle	()V
        //   59: return
        //   60: aconst_null
        //   61: astore 5
        //   63: goto -37 -> 26
        //   66: astore 4
        //   68: aload_3
        //   69: invokevirtual 44	android/os/Parcel:recycle	()V
        //   72: aload_2
        //   73: invokevirtual 44	android/os/Parcel:recycle	()V
        //   76: aload 4
        //   78: athrow
        // Local variable table:
        //   start	length	slot	name	signature
        //   0	79	0	this	zza
        //   0	79	1	paramzzv	zzv
        //   3	70	2	localParcel1	Parcel
        //   7	62	3	localParcel2	Parcel
        //   66	11	4	localObject	Object
        //   24	38	5	localIBinder	IBinder
        // Exception table:
        //   from	to	target	type
        //   8	14	66	finally
        //   18	26	66	finally
        //   26	51	66	finally
      }
      
      /* Error */
      public void zza(zzcl paramzzcl)
        throws RemoteException
      {
        // Byte code:
        //   0: invokestatic 26	android/os/Parcel:obtain	()Landroid/os/Parcel;
        //   3: astore_2
        //   4: invokestatic 26	android/os/Parcel:obtain	()Landroid/os/Parcel;
        //   7: astore_3
        //   8: aload_2
        //   9: ldc 28
        //   11: invokevirtual 32	android/os/Parcel:writeInterfaceToken	(Ljava/lang/String;)V
        //   14: aload_1
        //   15: ifnull +45 -> 60
        //   18: aload_1
        //   19: invokeinterface 98 1 0
        //   24: astore 5
        //   26: aload_2
        //   27: aload 5
        //   29: invokevirtual 82	android/os/Parcel:writeStrongBinder	(Landroid/os/IBinder;)V
        //   32: aload_0
        //   33: getfield 15	com/google/android/gms/ads/internal/client/zzs$zza$zza:zzoo	Landroid/os/IBinder;
        //   36: bipush 19
        //   38: aload_2
        //   39: aload_3
        //   40: iconst_0
        //   41: invokeinterface 38 5 0
        //   46: pop
        //   47: aload_3
        //   48: invokevirtual 41	android/os/Parcel:readException	()V
        //   51: aload_3
        //   52: invokevirtual 44	android/os/Parcel:recycle	()V
        //   55: aload_2
        //   56: invokevirtual 44	android/os/Parcel:recycle	()V
        //   59: return
        //   60: aconst_null
        //   61: astore 5
        //   63: goto -37 -> 26
        //   66: astore 4
        //   68: aload_3
        //   69: invokevirtual 44	android/os/Parcel:recycle	()V
        //   72: aload_2
        //   73: invokevirtual 44	android/os/Parcel:recycle	()V
        //   76: aload 4
        //   78: athrow
        // Local variable table:
        //   start	length	slot	name	signature
        //   0	79	0	this	zza
        //   0	79	1	paramzzcl	zzcl
        //   3	70	2	localParcel1	Parcel
        //   7	62	3	localParcel2	Parcel
        //   66	11	4	localObject	Object
        //   24	38	5	localIBinder	IBinder
        // Exception table:
        //   from	to	target	type
        //   8	14	66	finally
        //   18	26	66	finally
        //   26	51	66	finally
      }
      
      /* Error */
      public void zza(zzgc paramzzgc)
        throws RemoteException
      {
        // Byte code:
        //   0: invokestatic 26	android/os/Parcel:obtain	()Landroid/os/Parcel;
        //   3: astore_2
        //   4: invokestatic 26	android/os/Parcel:obtain	()Landroid/os/Parcel;
        //   7: astore_3
        //   8: aload_2
        //   9: ldc 28
        //   11: invokevirtual 32	android/os/Parcel:writeInterfaceToken	(Ljava/lang/String;)V
        //   14: aload_1
        //   15: ifnull +45 -> 60
        //   18: aload_1
        //   19: invokeinterface 102 1 0
        //   24: astore 5
        //   26: aload_2
        //   27: aload 5
        //   29: invokevirtual 82	android/os/Parcel:writeStrongBinder	(Landroid/os/IBinder;)V
        //   32: aload_0
        //   33: getfield 15	com/google/android/gms/ads/internal/client/zzs$zza$zza:zzoo	Landroid/os/IBinder;
        //   36: bipush 14
        //   38: aload_2
        //   39: aload_3
        //   40: iconst_0
        //   41: invokeinterface 38 5 0
        //   46: pop
        //   47: aload_3
        //   48: invokevirtual 41	android/os/Parcel:readException	()V
        //   51: aload_3
        //   52: invokevirtual 44	android/os/Parcel:recycle	()V
        //   55: aload_2
        //   56: invokevirtual 44	android/os/Parcel:recycle	()V
        //   59: return
        //   60: aconst_null
        //   61: astore 5
        //   63: goto -37 -> 26
        //   66: astore 4
        //   68: aload_3
        //   69: invokevirtual 44	android/os/Parcel:recycle	()V
        //   72: aload_2
        //   73: invokevirtual 44	android/os/Parcel:recycle	()V
        //   76: aload 4
        //   78: athrow
        // Local variable table:
        //   start	length	slot	name	signature
        //   0	79	0	this	zza
        //   0	79	1	paramzzgc	zzgc
        //   3	70	2	localParcel1	Parcel
        //   7	62	3	localParcel2	Parcel
        //   66	11	4	localObject	Object
        //   24	38	5	localIBinder	IBinder
        // Exception table:
        //   from	to	target	type
        //   8	14	66	finally
        //   18	26	66	finally
        //   26	51	66	finally
      }
      
      /* Error */
      public void zza(zzgg paramzzgg, String paramString)
        throws RemoteException
      {
        // Byte code:
        //   0: invokestatic 26	android/os/Parcel:obtain	()Landroid/os/Parcel;
        //   3: astore_3
        //   4: invokestatic 26	android/os/Parcel:obtain	()Landroid/os/Parcel;
        //   7: astore 4
        //   9: aload_3
        //   10: ldc 28
        //   12: invokevirtual 32	android/os/Parcel:writeInterfaceToken	(Ljava/lang/String;)V
        //   15: aload_1
        //   16: ifnull +53 -> 69
        //   19: aload_1
        //   20: invokeinterface 106 1 0
        //   25: astore 6
        //   27: aload_3
        //   28: aload 6
        //   30: invokevirtual 82	android/os/Parcel:writeStrongBinder	(Landroid/os/IBinder;)V
        //   33: aload_3
        //   34: aload_2
        //   35: invokevirtual 109	android/os/Parcel:writeString	(Ljava/lang/String;)V
        //   38: aload_0
        //   39: getfield 15	com/google/android/gms/ads/internal/client/zzs$zza$zza:zzoo	Landroid/os/IBinder;
        //   42: bipush 15
        //   44: aload_3
        //   45: aload 4
        //   47: iconst_0
        //   48: invokeinterface 38 5 0
        //   53: pop
        //   54: aload 4
        //   56: invokevirtual 41	android/os/Parcel:readException	()V
        //   59: aload 4
        //   61: invokevirtual 44	android/os/Parcel:recycle	()V
        //   64: aload_3
        //   65: invokevirtual 44	android/os/Parcel:recycle	()V
        //   68: return
        //   69: aconst_null
        //   70: astore 6
        //   72: goto -45 -> 27
        //   75: astore 5
        //   77: aload 4
        //   79: invokevirtual 44	android/os/Parcel:recycle	()V
        //   82: aload_3
        //   83: invokevirtual 44	android/os/Parcel:recycle	()V
        //   86: aload 5
        //   88: athrow
        // Local variable table:
        //   start	length	slot	name	signature
        //   0	89	0	this	zza
        //   0	89	1	paramzzgg	zzgg
        //   0	89	2	paramString	String
        //   3	80	3	localParcel1	Parcel
        //   7	71	4	localParcel2	Parcel
        //   75	12	5	localObject	Object
        //   25	46	6	localIBinder	IBinder
        // Exception table:
        //   from	to	target	type
        //   9	15	75	finally
        //   19	27	75	finally
        //   27	59	75	finally
      }
      
      public zzd zzaO()
        throws RemoteException
      {
        Parcel localParcel1 = Parcel.obtain();
        Parcel localParcel2 = Parcel.obtain();
        try
        {
          localParcel1.writeInterfaceToken("com.google.android.gms.ads.internal.client.IAdManager");
          this.zzoo.transact(1, localParcel1, localParcel2, 0);
          localParcel2.readException();
          zzd localzzd = zzd.zza.zzbs(localParcel2.readStrongBinder());
          return localzzd;
        }
        finally
        {
          localParcel2.recycle();
          localParcel1.recycle();
        }
      }
      
      /* Error */
      public AdSizeParcel zzaP()
        throws RemoteException
      {
        // Byte code:
        //   0: invokestatic 26	android/os/Parcel:obtain	()Landroid/os/Parcel;
        //   3: astore_1
        //   4: invokestatic 26	android/os/Parcel:obtain	()Landroid/os/Parcel;
        //   7: astore_2
        //   8: aload_1
        //   9: ldc 28
        //   11: invokevirtual 32	android/os/Parcel:writeInterfaceToken	(Ljava/lang/String;)V
        //   14: aload_0
        //   15: getfield 15	com/google/android/gms/ads/internal/client/zzs$zza$zza:zzoo	Landroid/os/IBinder;
        //   18: bipush 12
        //   20: aload_1
        //   21: aload_2
        //   22: iconst_0
        //   23: invokeinterface 38 5 0
        //   28: pop
        //   29: aload_2
        //   30: invokevirtual 41	android/os/Parcel:readException	()V
        //   33: aload_2
        //   34: invokevirtual 55	android/os/Parcel:readInt	()I
        //   37: ifeq +27 -> 64
        //   40: getstatic 126	com/google/android/gms/ads/internal/client/AdSizeParcel:CREATOR	Lcom/google/android/gms/ads/internal/client/zzi;
        //   43: aload_2
        //   44: invokevirtual 132	com/google/android/gms/ads/internal/client/zzi:zzc	(Landroid/os/Parcel;)Lcom/google/android/gms/ads/internal/client/AdSizeParcel;
        //   47: astore 6
        //   49: aload 6
        //   51: astore 5
        //   53: aload_2
        //   54: invokevirtual 44	android/os/Parcel:recycle	()V
        //   57: aload_1
        //   58: invokevirtual 44	android/os/Parcel:recycle	()V
        //   61: aload 5
        //   63: areturn
        //   64: aconst_null
        //   65: astore 5
        //   67: goto -14 -> 53
        //   70: astore_3
        //   71: aload_2
        //   72: invokevirtual 44	android/os/Parcel:recycle	()V
        //   75: aload_1
        //   76: invokevirtual 44	android/os/Parcel:recycle	()V
        //   79: aload_3
        //   80: athrow
        // Local variable table:
        //   start	length	slot	name	signature
        //   0	81	0	this	zza
        //   3	73	1	localParcel1	Parcel
        //   7	65	2	localParcel2	Parcel
        //   70	10	3	localObject	Object
        //   51	15	5	localAdSizeParcel1	AdSizeParcel
        //   47	3	6	localAdSizeParcel2	AdSizeParcel
        // Exception table:
        //   from	to	target	type
        //   8	49	70	finally
      }
      
      public void zzaR()
        throws RemoteException
      {
        Parcel localParcel1 = Parcel.obtain();
        Parcel localParcel2 = Parcel.obtain();
        try
        {
          localParcel1.writeInterfaceToken("com.google.android.gms.ads.internal.client.IAdManager");
          this.zzoo.transact(11, localParcel1, localParcel2, 0);
          localParcel2.readException();
          return;
        }
        finally
        {
          localParcel2.recycle();
          localParcel1.recycle();
        }
      }
      
      public boolean zzb(AdRequestParcel paramAdRequestParcel)
        throws RemoteException
      {
        boolean bool = true;
        Parcel localParcel1 = Parcel.obtain();
        Parcel localParcel2 = Parcel.obtain();
        for (;;)
        {
          try
          {
            localParcel1.writeInterfaceToken("com.google.android.gms.ads.internal.client.IAdManager");
            if (paramAdRequestParcel != null)
            {
              localParcel1.writeInt(1);
              paramAdRequestParcel.writeToParcel(localParcel1, 0);
              this.zzoo.transact(4, localParcel1, localParcel2, 0);
              localParcel2.readException();
              int i = localParcel2.readInt();
              if (i != 0) {
                return bool;
              }
            }
            else
            {
              localParcel1.writeInt(0);
              continue;
            }
            bool = false;
          }
          finally
          {
            localParcel2.recycle();
            localParcel1.recycle();
          }
        }
      }
    }
  }
}


/* Location:              D:\Apk\dex2jar-0.0.9.15\classes-dex2jar.jar!\com\google\android\gms\ads\internal\client\zzs.class
 * Java compiler version: 6 (50.0)
 * JD-Core Version:       0.7.1
 */