package com.purplebrain.adbuddiz.sdk.h;

public final class j
  extends a
{
  public a e;
  
  /* Error */
  protected final void c()
  {
    // Byte code:
    //   0: aconst_null
    //   1: astore_1
    //   2: invokestatic 25	com/purplebrain/adbuddiz/sdk/AdBuddiz:getContext	()Landroid/content/Context;
    //   5: astore_2
    //   6: lconst_0
    //   7: lstore_3
    //   8: aload_2
    //   9: ldc 27
    //   11: iconst_0
    //   12: invokevirtual 33	android/content/Context:getSharedPreferences	(Ljava/lang/String;I)Landroid/content/SharedPreferences;
    //   15: ldc 35
    //   17: ldc2_w 36
    //   20: invokeinterface 43 4 0
    //   25: invokestatic 49	java/lang/Long:valueOf	(J)Ljava/lang/Long;
    //   28: invokevirtual 53	java/lang/Long:longValue	()J
    //   31: ldc2_w 36
    //   34: lcmp
    //   35: ifeq +34 -> 69
    //   38: iconst_1
    //   39: istore 5
    //   41: iload 5
    //   43: ifne +32 -> 75
    //   46: lload_3
    //   47: ldc2_w 54
    //   50: lcmp
    //   51: ifge +24 -> 75
    //   54: ldc2_w 56
    //   57: invokestatic 63	java/lang/Thread:sleep	(J)V
    //   60: lload_3
    //   61: ldc2_w 56
    //   64: ladd
    //   65: lstore_3
    //   66: goto -58 -> 8
    //   69: iconst_0
    //   70: istore 5
    //   72: goto -31 -> 41
    //   75: invokestatic 68	com/purplebrain/adbuddiz/sdk/i/w:c	()Ljava/net/URL;
    //   78: astore 11
    //   80: invokestatic 25	com/purplebrain/adbuddiz/sdk/AdBuddiz:getContext	()Landroid/content/Context;
    //   83: astore 12
    //   85: new 70	org/json/JSONObject
    //   88: dup
    //   89: invokespecial 71	org/json/JSONObject:<init>	()V
    //   92: astore 13
    //   94: new 73	com/purplebrain/adbuddiz/sdk/h/a/a$a
    //   97: dup
    //   98: invokespecial 74	com/purplebrain/adbuddiz/sdk/h/a/a$a:<init>	()V
    //   101: pop
    //   102: aload 13
    //   104: ldc 76
    //   106: aload 12
    //   108: invokestatic 79	com/purplebrain/adbuddiz/sdk/h/a/a$a:a	(Landroid/content/Context;)Lcom/purplebrain/adbuddiz/sdk/h/a/a;
    //   111: invokevirtual 84	com/purplebrain/adbuddiz/sdk/h/a/a:a	()Lorg/json/JSONObject;
    //   114: invokevirtual 88	org/json/JSONObject:put	(Ljava/lang/String;Ljava/lang/Object;)Lorg/json/JSONObject;
    //   117: pop
    //   118: new 90	com/purplebrain/adbuddiz/sdk/h/a/b$a
    //   121: dup
    //   122: invokespecial 91	com/purplebrain/adbuddiz/sdk/h/a/b$a:<init>	()V
    //   125: pop
    //   126: aload 13
    //   128: ldc 93
    //   130: aload 12
    //   132: invokestatic 96	com/purplebrain/adbuddiz/sdk/h/a/b$a:a	(Landroid/content/Context;)Lcom/purplebrain/adbuddiz/sdk/h/a/b;
    //   135: invokevirtual 99	com/purplebrain/adbuddiz/sdk/h/a/b:a	()Lorg/json/JSONObject;
    //   138: invokevirtual 88	org/json/JSONObject:put	(Ljava/lang/String;Ljava/lang/Object;)Lorg/json/JSONObject;
    //   141: pop
    //   142: new 101	com/purplebrain/adbuddiz/sdk/h/a/d$a
    //   145: dup
    //   146: invokespecial 102	com/purplebrain/adbuddiz/sdk/h/a/d$a:<init>	()V
    //   149: pop
    //   150: aload 13
    //   152: ldc 104
    //   154: aload 12
    //   156: invokestatic 107	com/purplebrain/adbuddiz/sdk/h/a/d$a:a	(Landroid/content/Context;)Lcom/purplebrain/adbuddiz/sdk/h/a/d;
    //   159: invokevirtual 110	com/purplebrain/adbuddiz/sdk/h/a/d:a	()Lorg/json/JSONObject;
    //   162: invokevirtual 88	org/json/JSONObject:put	(Ljava/lang/String;Ljava/lang/Object;)Lorg/json/JSONObject;
    //   165: pop
    //   166: aload 13
    //   168: ldc 112
    //   170: aload 12
    //   172: invokestatic 117	com/purplebrain/adbuddiz/sdk/i/u:a	(Landroid/content/Context;)Z
    //   175: invokevirtual 120	org/json/JSONObject:put	(Ljava/lang/String;Z)Lorg/json/JSONObject;
    //   178: pop
    //   179: aload 13
    //   181: ldc 122
    //   183: invokestatic 127	com/purplebrain/adbuddiz/sdk/i/a/d:a	()Lcom/purplebrain/adbuddiz/sdk/f/e;
    //   186: getfield 132	com/purplebrain/adbuddiz/sdk/f/e:d	Ljava/lang/String;
    //   189: invokevirtual 88	org/json/JSONObject:put	(Ljava/lang/String;Ljava/lang/Object;)Lorg/json/JSONObject;
    //   192: pop
    //   193: aload 13
    //   195: ldc -122
    //   197: invokestatic 139	java/lang/System:currentTimeMillis	()J
    //   200: invokevirtual 142	org/json/JSONObject:put	(Ljava/lang/String;J)Lorg/json/JSONObject;
    //   203: pop
    //   204: aload 13
    //   206: invokevirtual 146	org/json/JSONObject:toString	()Ljava/lang/String;
    //   209: astore 23
    //   211: aload 11
    //   213: ldc -108
    //   215: invokestatic 153	com/purplebrain/adbuddiz/sdk/h/b:a	(Ljava/net/URL;Ljava/lang/String;)Ljava/net/HttpURLConnection;
    //   218: astore 7
    //   220: aload_0
    //   221: aload 7
    //   223: aload 23
    //   225: invokespecial 156	com/purplebrain/adbuddiz/sdk/h/b:a	(Ljava/net/HttpURLConnection;Ljava/lang/String;)V
    //   228: aload 7
    //   230: invokevirtual 162	java/net/HttpURLConnection:getResponseCode	()I
    //   233: istore 24
    //   235: aload_0
    //   236: aload 7
    //   238: invokevirtual 166	com/purplebrain/adbuddiz/sdk/h/j:b	(Ljava/net/HttpURLConnection;)Ljava/lang/String;
    //   241: astore 25
    //   243: aload_0
    //   244: getfield 168	com/purplebrain/adbuddiz/sdk/h/j:e	Lcom/purplebrain/adbuddiz/sdk/h/j$a;
    //   247: iload 24
    //   249: aload 25
    //   251: invokeinterface 173 3 0
    //   256: iload 24
    //   258: sipush 200
    //   261: if_icmpne +38 -> 299
    //   264: aload 25
    //   266: ifnull +22 -> 288
    //   269: aload 25
    //   271: invokevirtual 178	java/lang/String:length	()I
    //   274: ifle +14 -> 288
    //   277: aload_0
    //   278: getfield 168	com/purplebrain/adbuddiz/sdk/h/j:e	Lcom/purplebrain/adbuddiz/sdk/h/j$a;
    //   281: aload 25
    //   283: invokeinterface 181 2 0
    //   288: aload 7
    //   290: ifnull +8 -> 298
    //   293: aload 7
    //   295: invokevirtual 184	java/net/HttpURLConnection:disconnect	()V
    //   298: return
    //   299: iload 24
    //   301: sipush 500
    //   304: if_icmplt -16 -> 288
    //   307: new 186	com/purplebrain/adbuddiz/sdk/h/k
    //   310: dup
    //   311: new 188	java/lang/StringBuilder
    //   314: dup
    //   315: ldc -66
    //   317: invokespecial 192	java/lang/StringBuilder:<init>	(Ljava/lang/String;)V
    //   320: iload 24
    //   322: invokevirtual 196	java/lang/StringBuilder:append	(I)Ljava/lang/StringBuilder;
    //   325: invokevirtual 197	java/lang/StringBuilder:toString	()Ljava/lang/String;
    //   328: invokespecial 198	com/purplebrain/adbuddiz/sdk/h/k:<init>	(Ljava/lang/String;)V
    //   331: athrow
    //   332: astore 6
    //   334: aload_0
    //   335: getfield 168	com/purplebrain/adbuddiz/sdk/h/j:e	Lcom/purplebrain/adbuddiz/sdk/h/j$a;
    //   338: iconst_m1
    //   339: aconst_null
    //   340: invokeinterface 173 3 0
    //   345: aload 6
    //   347: athrow
    //   348: astore 8
    //   350: aload 7
    //   352: astore_1
    //   353: aload_1
    //   354: ifnull +7 -> 361
    //   357: aload_1
    //   358: invokevirtual 184	java/net/HttpURLConnection:disconnect	()V
    //   361: aload 8
    //   363: athrow
    //   364: astore 10
    //   366: aload_0
    //   367: getfield 168	com/purplebrain/adbuddiz/sdk/h/j:e	Lcom/purplebrain/adbuddiz/sdk/h/j$a;
    //   370: iconst_m1
    //   371: aconst_null
    //   372: invokeinterface 173 3 0
    //   377: aload 10
    //   379: athrow
    //   380: aload_0
    //   381: getfield 168	com/purplebrain/adbuddiz/sdk/h/j:e	Lcom/purplebrain/adbuddiz/sdk/h/j$a;
    //   384: iconst_m1
    //   385: aconst_null
    //   386: invokeinterface 173 3 0
    //   391: aload 9
    //   393: athrow
    //   394: astore 26
    //   396: goto -388 -> 8
    //   399: astore 9
    //   401: aload 7
    //   403: astore_1
    //   404: goto -24 -> 380
    //   407: astore 10
    //   409: aload 7
    //   411: astore_1
    //   412: goto -46 -> 366
    //   415: astore 6
    //   417: aconst_null
    //   418: astore 7
    //   420: goto -86 -> 334
    //   423: astore 8
    //   425: goto -72 -> 353
    //   428: astore 9
    //   430: aconst_null
    //   431: astore_1
    //   432: goto -52 -> 380
    // Local variable table:
    //   start	length	slot	name	signature
    //   0	435	0	this	j
    //   1	431	1	localObject1	Object
    //   5	4	2	localContext1	android.content.Context
    //   7	59	3	l	long
    //   39	32	5	i	int
    //   332	14	6	localUnknownHostException1	java.net.UnknownHostException
    //   415	1	6	localUnknownHostException2	java.net.UnknownHostException
    //   218	201	7	localHttpURLConnection	java.net.HttpURLConnection
    //   348	14	8	localObject2	Object
    //   423	1	8	localObject3	Object
    //   391	1	9	localObject4	Object
    //   399	1	9	localSocketTimeoutException1	java.net.SocketTimeoutException
    //   428	1	9	localSocketTimeoutException2	java.net.SocketTimeoutException
    //   364	14	10	localConnectException1	java.net.ConnectException
    //   407	1	10	localConnectException2	java.net.ConnectException
    //   78	134	11	localURL	java.net.URL
    //   83	88	12	localContext2	android.content.Context
    //   92	113	13	localJSONObject	org.json.JSONObject
    //   209	15	23	str1	String
    //   233	88	24	j	int
    //   241	41	25	str2	String
    //   394	1	26	localInterruptedException	InterruptedException
    // Exception table:
    //   from	to	target	type
    //   228	256	332	java/net/UnknownHostException
    //   269	288	332	java/net/UnknownHostException
    //   307	332	332	java/net/UnknownHostException
    //   228	256	348	finally
    //   269	288	348	finally
    //   307	332	348	finally
    //   334	348	348	finally
    //   75	228	364	java/net/ConnectException
    //   54	60	394	java/lang/InterruptedException
    //   228	256	399	java/net/SocketTimeoutException
    //   269	288	399	java/net/SocketTimeoutException
    //   307	332	399	java/net/SocketTimeoutException
    //   228	256	407	java/net/ConnectException
    //   269	288	407	java/net/ConnectException
    //   307	332	407	java/net/ConnectException
    //   75	228	415	java/net/UnknownHostException
    //   75	228	423	finally
    //   366	380	423	finally
    //   380	394	423	finally
    //   75	228	428	java/net/SocketTimeoutException
  }
  
  protected final boolean d()
  {
    return false;
  }
  
  protected final String e()
  {
    return "UpdateConf";
  }
  
  public static abstract interface a
  {
    public abstract void a(int paramInt, String paramString);
    
    public abstract void b(String paramString);
  }
}


/* Location:              D:\Apk\dex2jar-0.0.9.15\classes-dex2jar.jar!\com\purplebrain\adbuddiz\sdk\h\j.class
 * Java compiler version: 6 (50.0)
 * JD-Core Version:       0.7.1
 */