package com.google.android.gms.internal;

import android.content.Context;
import android.util.DisplayMetrics;
import android.view.MotionEvent;
import com.google.ads.afma.nano.NanoAdshieldEvent.AdShieldEvent;
import com.google.android.gms.clearcut.zza;
import com.google.android.gms.clearcut.zza.zza;
import com.google.android.gms.common.GoogleApiAvailability;
import com.google.android.gms.common.api.GoogleApiClient;
import com.google.android.gms.common.api.GoogleApiClient.Builder;
import dalvik.system.DexClassLoader;
import java.io.File;
import java.io.FileNotFoundException;
import java.io.FileOutputStream;
import java.io.IOException;
import java.io.UnsupportedEncodingException;
import java.lang.reflect.InvocationTargetException;
import java.lang.reflect.Method;
import java.nio.ByteBuffer;
import java.util.ArrayList;
import java.util.Random;
import java.util.concurrent.TimeUnit;

public abstract class zzal
  extends zzak
{
  private static long startTime = 0L;
  private static Method zznA;
  private static Method zznB;
  private static Method zznC;
  private static Method zznD;
  private static Method zznE;
  private static Method zznF;
  private static String zznG;
  private static String zznH;
  private static String zznI;
  private static zzar zznJ;
  static boolean zznK = false;
  protected static zza zznL = null;
  protected static NanoAdshieldEvent.AdShieldEvent zznM;
  protected static int zznN;
  private static Random zznO = new Random();
  private static GoogleApiAvailability zznP = GoogleApiAvailability.getInstance();
  private static boolean zznQ;
  protected static boolean zznR = false;
  protected static boolean zznS = false;
  protected static boolean zznT = false;
  protected static boolean zznU = false;
  private static Method zznt;
  private static Method zznu;
  private static Method zznv;
  private static Method zznw;
  private static Method zznx;
  private static Method zzny;
  private static Method zznz;
  
  protected zzal(Context paramContext, zzap paramzzap, zzaq paramzzaq)
  {
    super(paramContext, paramzzap, paramzzaq);
    zznM = new NanoAdshieldEvent.AdShieldEvent();
    zznM.appId = paramContext.getPackageName();
  }
  
  private void zzU()
  {
    if ((zznU) && (zznL != null))
    {
      zznL.zza(zznr, 100L, TimeUnit.MILLISECONDS);
      zznr.disconnect();
    }
  }
  
  static String zzV()
    throws zzal.zza
  {
    if (zznG == null) {
      throw new zza();
    }
    return zznG;
  }
  
  static Long zzW()
    throws zzal.zza
  {
    if (zznt == null) {
      throw new zza();
    }
    try
    {
      Long localLong = (Long)zznt.invoke(null, new Object[0]);
      return localLong;
    }
    catch (IllegalAccessException localIllegalAccessException)
    {
      throw new zza(localIllegalAccessException);
    }
    catch (InvocationTargetException localInvocationTargetException)
    {
      throw new zza(localInvocationTargetException);
    }
  }
  
  static String zzX()
    throws zzal.zza
  {
    if (zznv == null) {
      throw new zza();
    }
    try
    {
      String str = (String)zznv.invoke(null, new Object[0]);
      return str;
    }
    catch (IllegalAccessException localIllegalAccessException)
    {
      throw new zza(localIllegalAccessException);
    }
    catch (InvocationTargetException localInvocationTargetException)
    {
      throw new zza(localInvocationTargetException);
    }
  }
  
  static Long zzY()
    throws zzal.zza
  {
    if (zznu == null) {
      throw new zza();
    }
    try
    {
      Long localLong = (Long)zznu.invoke(null, new Object[0]);
      return localLong;
    }
    catch (IllegalAccessException localIllegalAccessException)
    {
      throw new zza(localIllegalAccessException);
    }
    catch (InvocationTargetException localInvocationTargetException)
    {
      throw new zza(localInvocationTargetException);
    }
  }
  
  static String zza(Context paramContext, zzap paramzzap)
    throws zzal.zza
  {
    if (zznH != null) {
      return zznH;
    }
    if (zznw == null) {
      throw new zza();
    }
    try
    {
      localByteBuffer = (ByteBuffer)zznw.invoke(null, new Object[] { paramContext });
      if (localByteBuffer == null) {
        throw new zza();
      }
    }
    catch (IllegalAccessException localIllegalAccessException)
    {
      ByteBuffer localByteBuffer;
      throw new zza(localIllegalAccessException);
      zznH = paramzzap.zza(localByteBuffer.array(), true);
      String str = zznH;
      return str;
    }
    catch (InvocationTargetException localInvocationTargetException)
    {
      throw new zza(localInvocationTargetException);
    }
  }
  
  static ArrayList<Long> zza(MotionEvent paramMotionEvent, DisplayMetrics paramDisplayMetrics)
    throws zzal.zza
  {
    if ((zznx == null) || (paramMotionEvent == null)) {
      throw new zza();
    }
    try
    {
      ArrayList localArrayList = (ArrayList)zznx.invoke(null, new Object[] { paramMotionEvent, paramDisplayMetrics });
      return localArrayList;
    }
    catch (IllegalAccessException localIllegalAccessException)
    {
      throw new zza(localIllegalAccessException);
    }
    catch (InvocationTargetException localInvocationTargetException)
    {
      throw new zza(localInvocationTargetException);
    }
  }
  
  protected static void zza(int paramInt1, int paramInt2)
    throws IOException
  {
    if ((zznU) && (zznR) && (zznL != null))
    {
      zza.zza localzza = zznL.zzi(zztk.toByteArray(zznM));
      localzza.zzbr(paramInt2);
      localzza.zzbq(paramInt1);
      localzza.zzc(zznr);
    }
  }
  
  protected static void zza(String paramString, Context paramContext, zzap paramzzap)
  {
    boolean bool1 = true;
    for (;;)
    {
      try
      {
        boolean bool2 = zznK;
        if (bool2) {}
      }
      finally {}
      try
      {
        zznJ = new zzar(paramzzap, null);
        zznG = paramString;
        zzbz.initialize(paramContext);
        zzm(paramContext);
        startTime = zzW().longValue();
        zznO = new Random();
      }
      catch (UnsupportedOperationException localUnsupportedOperationException)
      {
        continue;
      }
      catch (zza localzza)
      {
        continue;
      }
      try
      {
        zznr = new GoogleApiClient.Builder(paramContext).addApi(zza.API).build();
        zznP = GoogleApiAvailability.getInstance();
        if (zznP.isGooglePlayServicesAvailable(paramContext) != 0) {
          continue;
        }
        zznQ = bool1;
        zzbz.initialize(paramContext);
        zznR = ((Boolean)zzbz.zzwD.get()).booleanValue();
        zznL = new zza(paramContext, "ADSHIELD", null, null);
      }
      catch (NoClassDefFoundError localNoClassDefFoundError)
      {
        continue;
      }
      zznK = true;
      return;
      bool1 = false;
    }
  }
  
  static String zzb(Context paramContext, zzap paramzzap)
    throws zzal.zza
  {
    if (zznI != null) {
      return zznI;
    }
    if (zznz == null) {
      throw new zza();
    }
    try
    {
      localByteBuffer = (ByteBuffer)zznz.invoke(null, new Object[] { paramContext });
      if (localByteBuffer == null) {
        throw new zza();
      }
    }
    catch (IllegalAccessException localIllegalAccessException)
    {
      ByteBuffer localByteBuffer;
      throw new zza(localIllegalAccessException);
      zznI = paramzzap.zza(localByteBuffer.array(), true);
      String str = zznI;
      return str;
    }
    catch (InvocationTargetException localInvocationTargetException)
    {
      throw new zza(localInvocationTargetException);
    }
  }
  
  private static String zzb(byte[] paramArrayOfByte, String paramString)
    throws zzal.zza
  {
    try
    {
      String str = new String(zznJ.zzc(paramArrayOfByte, paramString), "UTF-8");
      return str;
    }
    catch (zzar.zza localzza)
    {
      throw new zza(localzza);
    }
    catch (UnsupportedEncodingException localUnsupportedEncodingException)
    {
      throw new zza(localUnsupportedEncodingException);
    }
  }
  
  private void zze(Context paramContext)
  {
    if (zznQ)
    {
      zznr.connect();
      zznU = true;
      return;
    }
    zznU = false;
  }
  
  static String zzf(Context paramContext)
    throws zzal.zza
  {
    if (zzny == null) {
      throw new zza();
    }
    String str;
    try
    {
      str = (String)zzny.invoke(null, new Object[] { paramContext });
      if (str == null) {
        throw new zza();
      }
    }
    catch (IllegalAccessException localIllegalAccessException)
    {
      throw new zza(localIllegalAccessException);
    }
    catch (InvocationTargetException localInvocationTargetException)
    {
      throw new zza(localInvocationTargetException);
    }
    return str;
  }
  
  static String zzg(Context paramContext)
    throws zzal.zza
  {
    if (zznC == null) {
      throw new zza();
    }
    try
    {
      String str = (String)zznC.invoke(null, new Object[] { paramContext });
      return str;
    }
    catch (IllegalAccessException localIllegalAccessException)
    {
      throw new zza(localIllegalAccessException);
    }
    catch (InvocationTargetException localInvocationTargetException)
    {
      throw new zza(localInvocationTargetException);
    }
  }
  
  static Long zzh(Context paramContext)
    throws zzal.zza
  {
    if (zznD == null) {
      throw new zza();
    }
    try
    {
      Long localLong = (Long)zznD.invoke(null, new Object[] { paramContext });
      return localLong;
    }
    catch (IllegalAccessException localIllegalAccessException)
    {
      throw new zza(localIllegalAccessException);
    }
    catch (InvocationTargetException localInvocationTargetException)
    {
      throw new zza(localInvocationTargetException);
    }
  }
  
  static ArrayList<Long> zzi(Context paramContext)
    throws zzal.zza
  {
    if (zznA == null) {
      throw new zza();
    }
    ArrayList localArrayList;
    try
    {
      localArrayList = (ArrayList)zznA.invoke(null, new Object[] { paramContext });
      if ((localArrayList == null) || (localArrayList.size() != 2)) {
        throw new zza();
      }
    }
    catch (IllegalAccessException localIllegalAccessException)
    {
      throw new zza(localIllegalAccessException);
    }
    catch (InvocationTargetException localInvocationTargetException)
    {
      throw new zza(localInvocationTargetException);
    }
    return localArrayList;
  }
  
  static int[] zzj(Context paramContext)
    throws zzal.zza
  {
    if (zznB == null) {
      throw new zza();
    }
    try
    {
      int[] arrayOfInt = (int[])zznB.invoke(null, new Object[] { paramContext });
      return arrayOfInt;
    }
    catch (IllegalAccessException localIllegalAccessException)
    {
      throw new zza(localIllegalAccessException);
    }
    catch (InvocationTargetException localInvocationTargetException)
    {
      throw new zza(localInvocationTargetException);
    }
  }
  
  static int zzk(Context paramContext)
    throws zzal.zza
  {
    if (zznE == null) {
      throw new zza();
    }
    try
    {
      int i = ((Integer)zznE.invoke(null, new Object[] { paramContext })).intValue();
      return i;
    }
    catch (IllegalAccessException localIllegalAccessException)
    {
      throw new zza(localIllegalAccessException);
    }
    catch (InvocationTargetException localInvocationTargetException)
    {
      throw new zza(localInvocationTargetException);
    }
  }
  
  static int zzl(Context paramContext)
    throws zzal.zza
  {
    if (zznF == null) {
      throw new zza();
    }
    try
    {
      int i = ((Integer)zznF.invoke(null, new Object[] { paramContext })).intValue();
      return i;
    }
    catch (IllegalAccessException localIllegalAccessException)
    {
      throw new zza(localIllegalAccessException);
    }
    catch (InvocationTargetException localInvocationTargetException)
    {
      throw new zza(localInvocationTargetException);
    }
  }
  
  private static void zzm(Context paramContext)
    throws zzal.zza
  {
    try
    {
      arrayOfByte1 = zznJ.zzl(zzat.getKey());
      arrayOfByte2 = zznJ.zzc(arrayOfByte1, zzat.zzae());
      localFile1 = paramContext.getCacheDir();
      if (localFile1 == null)
      {
        localFile1 = paramContext.getDir("dex", 0);
        if (localFile1 == null) {
          throw new zza();
        }
      }
    }
    catch (FileNotFoundException localFileNotFoundException)
    {
      byte[] arrayOfByte1;
      byte[] arrayOfByte2;
      File localFile1;
      throw new zza(localFileNotFoundException);
      File localFile2 = localFile1;
      File localFile3 = File.createTempFile("ads", ".jar", localFile2);
      FileOutputStream localFileOutputStream = new FileOutputStream(localFile3);
      localFileOutputStream.write(arrayOfByte2, 0, arrayOfByte2.length);
      localFileOutputStream.close();
      try
      {
        DexClassLoader localDexClassLoader = new DexClassLoader(localFile3.getAbsolutePath(), localFile2.getAbsolutePath(), null, paramContext.getClassLoader());
        Class localClass1 = localDexClassLoader.loadClass(zzb(arrayOfByte1, zzat.zzan()));
        Class localClass2 = localDexClassLoader.loadClass(zzb(arrayOfByte1, zzat.zzaB()));
        Class localClass3 = localDexClassLoader.loadClass(zzb(arrayOfByte1, zzat.zzav()));
        Class localClass4 = localDexClassLoader.loadClass(zzb(arrayOfByte1, zzat.zzar()));
        Class localClass5 = localDexClassLoader.loadClass(zzb(arrayOfByte1, zzat.zzaD()));
        Class localClass6 = localDexClassLoader.loadClass(zzb(arrayOfByte1, zzat.zzap()));
        Class localClass7 = localDexClassLoader.loadClass(zzb(arrayOfByte1, zzat.zzaz()));
        Class localClass8 = localDexClassLoader.loadClass(zzb(arrayOfByte1, zzat.zzax()));
        Class localClass9 = localDexClassLoader.loadClass(zzb(arrayOfByte1, zzat.zzal()));
        Class localClass10 = localDexClassLoader.loadClass(zzb(arrayOfByte1, zzat.zzaj()));
        Class localClass11 = localDexClassLoader.loadClass(zzb(arrayOfByte1, zzat.zzah()));
        Class localClass12 = localDexClassLoader.loadClass(zzb(arrayOfByte1, zzat.zzat()));
        Class localClass13 = localDexClassLoader.loadClass(zzb(arrayOfByte1, zzat.zzaf()));
        zznt = localClass1.getMethod(zzb(arrayOfByte1, zzat.zzao()), new Class[0]);
        zznu = localClass2.getMethod(zzb(arrayOfByte1, zzat.zzaC()), new Class[0]);
        zznv = localClass3.getMethod(zzb(arrayOfByte1, zzat.zzaw()), new Class[0]);
        zznw = localClass4.getMethod(zzb(arrayOfByte1, zzat.zzas()), new Class[] { Context.class });
        zznx = localClass5.getMethod(zzb(arrayOfByte1, zzat.zzaE()), new Class[] { MotionEvent.class, DisplayMetrics.class });
        zzny = localClass6.getMethod(zzb(arrayOfByte1, zzat.zzaq()), new Class[] { Context.class });
        zznz = localClass7.getMethod(zzb(arrayOfByte1, zzat.zzaA()), new Class[] { Context.class });
        zznA = localClass8.getMethod(zzb(arrayOfByte1, zzat.zzay()), new Class[] { Context.class });
        zznB = localClass9.getMethod(zzb(arrayOfByte1, zzat.zzam()), new Class[] { Context.class });
        zznC = localClass10.getMethod(zzb(arrayOfByte1, zzat.zzak()), new Class[] { Context.class });
        zznD = localClass11.getMethod(zzb(arrayOfByte1, zzat.zzai()), new Class[] { Context.class });
        zznE = localClass12.getMethod(zzb(arrayOfByte1, zzat.zzau()), new Class[] { Context.class });
        zznF = localClass13.getMethod(zzb(arrayOfByte1, zzat.zzag()), new Class[] { Context.class });
        String str2;
        return;
      }
      finally
      {
        String str1 = localFile3.getName();
        localFile3.delete();
        new File(localFile2, str1.replace(".jar", ".dex")).delete();
      }
    }
    catch (IOException localIOException)
    {
      throw new zza(localIOException);
    }
    catch (ClassNotFoundException localClassNotFoundException)
    {
      throw new zza(localClassNotFoundException);
    }
    catch (zzar.zza localzza)
    {
      throw new zza(localzza);
    }
    catch (NoSuchMethodException localNoSuchMethodException)
    {
      throw new zza(localNoSuchMethodException);
    }
    catch (NullPointerException localNullPointerException)
    {
      throw new zza(localNullPointerException);
    }
  }
  
  /* Error */
  protected void zzc(Context paramContext)
  {
    // Byte code:
    //   0: aload_0
    //   1: aload_1
    //   2: invokespecial 498	com/google/android/gms/internal/zzal:zze	(Landroid/content/Context;)V
    //   5: getstatic 58	com/google/android/gms/internal/zzal:zznO	Ljava/util/Random;
    //   8: invokevirtual 501	java/util/Random:nextInt	()I
    //   11: putstatic 503	com/google/android/gms/internal/zzal:zznN	I
    //   14: iconst_0
    //   15: getstatic 503	com/google/android/gms/internal/zzal:zznN	I
    //   18: invokestatic 505	com/google/android/gms/internal/zzal:zza	(II)V
    //   21: aload_0
    //   22: iconst_1
    //   23: invokestatic 507	com/google/android/gms/internal/zzal:zzX	()Ljava/lang/String;
    //   26: invokevirtual 510	com/google/android/gms/internal/zzal:zza	(ILjava/lang/String;)V
    //   29: iconst_1
    //   30: getstatic 503	com/google/android/gms/internal/zzal:zznN	I
    //   33: invokestatic 505	com/google/android/gms/internal/zzal:zza	(II)V
    //   36: aload_0
    //   37: iconst_2
    //   38: invokestatic 512	com/google/android/gms/internal/zzal:zzV	()Ljava/lang/String;
    //   41: invokevirtual 510	com/google/android/gms/internal/zzal:zza	(ILjava/lang/String;)V
    //   44: iconst_2
    //   45: getstatic 503	com/google/android/gms/internal/zzal:zznN	I
    //   48: invokestatic 505	com/google/android/gms/internal/zzal:zza	(II)V
    //   51: invokestatic 220	com/google/android/gms/internal/zzal:zzW	()Ljava/lang/Long;
    //   54: invokevirtual 224	java/lang/Long:longValue	()J
    //   57: lstore 17
    //   59: aload_0
    //   60: bipush 25
    //   62: lload 17
    //   64: invokevirtual 515	com/google/android/gms/internal/zzal:zza	(IJ)V
    //   67: getstatic 47	com/google/android/gms/internal/zzal:startTime	J
    //   70: lconst_0
    //   71: lcmp
    //   72: ifeq +24 -> 96
    //   75: aload_0
    //   76: bipush 17
    //   78: lload 17
    //   80: getstatic 47	com/google/android/gms/internal/zzal:startTime	J
    //   83: lsub
    //   84: invokevirtual 515	com/google/android/gms/internal/zzal:zza	(IJ)V
    //   87: aload_0
    //   88: bipush 23
    //   90: getstatic 47	com/google/android/gms/internal/zzal:startTime	J
    //   93: invokevirtual 515	com/google/android/gms/internal/zzal:zza	(IJ)V
    //   96: bipush 25
    //   98: getstatic 503	com/google/android/gms/internal/zzal:zznN	I
    //   101: invokestatic 505	com/google/android/gms/internal/zzal:zza	(II)V
    //   104: aload_1
    //   105: invokestatic 517	com/google/android/gms/internal/zzal:zzi	(Landroid/content/Context;)Ljava/util/ArrayList;
    //   108: astore 16
    //   110: aload_0
    //   111: bipush 31
    //   113: aload 16
    //   115: iconst_0
    //   116: invokevirtual 520	java/util/ArrayList:get	(I)Ljava/lang/Object;
    //   119: checkcast 139	java/lang/Long
    //   122: invokevirtual 224	java/lang/Long:longValue	()J
    //   125: invokevirtual 515	com/google/android/gms/internal/zzal:zza	(IJ)V
    //   128: aload_0
    //   129: bipush 32
    //   131: aload 16
    //   133: iconst_1
    //   134: invokevirtual 520	java/util/ArrayList:get	(I)Ljava/lang/Object;
    //   137: checkcast 139	java/lang/Long
    //   140: invokevirtual 224	java/lang/Long:longValue	()J
    //   143: invokevirtual 515	com/google/android/gms/internal/zzal:zza	(IJ)V
    //   146: bipush 31
    //   148: getstatic 503	com/google/android/gms/internal/zzal:zznN	I
    //   151: invokestatic 505	com/google/android/gms/internal/zzal:zza	(II)V
    //   154: aload_0
    //   155: bipush 33
    //   157: invokestatic 522	com/google/android/gms/internal/zzal:zzY	()Ljava/lang/Long;
    //   160: invokevirtual 224	java/lang/Long:longValue	()J
    //   163: invokevirtual 515	com/google/android/gms/internal/zzal:zza	(IJ)V
    //   166: bipush 33
    //   168: getstatic 503	com/google/android/gms/internal/zzal:zznN	I
    //   171: invokestatic 505	com/google/android/gms/internal/zzal:zza	(II)V
    //   174: getstatic 70	com/google/android/gms/internal/zzal:zznS	Z
    //   177: ifeq +153 -> 330
    //   180: getstatic 72	com/google/android/gms/internal/zzal:zznT	Z
    //   183: ifeq +147 -> 330
    //   186: bipush 27
    //   188: getstatic 503	com/google/android/gms/internal/zzal:zznN	I
    //   191: invokestatic 505	com/google/android/gms/internal/zzal:zza	(II)V
    //   194: aload_0
    //   195: bipush 29
    //   197: aload_1
    //   198: aload_0
    //   199: getfield 526	com/google/android/gms/internal/zzal:zznq	Lcom/google/android/gms/internal/zzap;
    //   202: invokestatic 528	com/google/android/gms/internal/zzal:zzb	(Landroid/content/Context;Lcom/google/android/gms/internal/zzap;)Ljava/lang/String;
    //   205: invokevirtual 510	com/google/android/gms/internal/zzal:zza	(ILjava/lang/String;)V
    //   208: bipush 29
    //   210: getstatic 503	com/google/android/gms/internal/zzal:zznN	I
    //   213: invokestatic 505	com/google/android/gms/internal/zzal:zza	(II)V
    //   216: aload_1
    //   217: invokestatic 530	com/google/android/gms/internal/zzal:zzj	(Landroid/content/Context;)[I
    //   220: astore 15
    //   222: aload_0
    //   223: iconst_5
    //   224: aload 15
    //   226: iconst_0
    //   227: iaload
    //   228: i2l
    //   229: invokevirtual 515	com/google/android/gms/internal/zzal:zza	(IJ)V
    //   232: aload_0
    //   233: bipush 6
    //   235: aload 15
    //   237: iconst_1
    //   238: iaload
    //   239: i2l
    //   240: invokevirtual 515	com/google/android/gms/internal/zzal:zza	(IJ)V
    //   243: iconst_5
    //   244: getstatic 503	com/google/android/gms/internal/zzal:zznN	I
    //   247: invokestatic 505	com/google/android/gms/internal/zzal:zza	(II)V
    //   250: aload_0
    //   251: bipush 12
    //   253: aload_1
    //   254: invokestatic 532	com/google/android/gms/internal/zzal:zzk	(Landroid/content/Context;)I
    //   257: i2l
    //   258: invokevirtual 515	com/google/android/gms/internal/zzal:zza	(IJ)V
    //   261: bipush 12
    //   263: getstatic 503	com/google/android/gms/internal/zzal:zznN	I
    //   266: invokestatic 505	com/google/android/gms/internal/zzal:zza	(II)V
    //   269: aload_0
    //   270: iconst_3
    //   271: aload_1
    //   272: invokestatic 534	com/google/android/gms/internal/zzal:zzl	(Landroid/content/Context;)I
    //   275: i2l
    //   276: invokevirtual 515	com/google/android/gms/internal/zzal:zza	(IJ)V
    //   279: iconst_3
    //   280: getstatic 503	com/google/android/gms/internal/zzal:zznN	I
    //   283: invokestatic 505	com/google/android/gms/internal/zzal:zza	(II)V
    //   286: aload_0
    //   287: bipush 34
    //   289: aload_1
    //   290: invokestatic 536	com/google/android/gms/internal/zzal:zzg	(Landroid/content/Context;)Ljava/lang/String;
    //   293: invokevirtual 510	com/google/android/gms/internal/zzal:zza	(ILjava/lang/String;)V
    //   296: bipush 34
    //   298: getstatic 503	com/google/android/gms/internal/zzal:zznN	I
    //   301: invokestatic 505	com/google/android/gms/internal/zzal:zza	(II)V
    //   304: aload_0
    //   305: bipush 35
    //   307: aload_1
    //   308: invokestatic 538	com/google/android/gms/internal/zzal:zzh	(Landroid/content/Context;)Ljava/lang/Long;
    //   311: invokevirtual 224	java/lang/Long:longValue	()J
    //   314: invokevirtual 515	com/google/android/gms/internal/zzal:zza	(IJ)V
    //   317: bipush 35
    //   319: getstatic 503	com/google/android/gms/internal/zzal:zznN	I
    //   322: invokestatic 505	com/google/android/gms/internal/zzal:zza	(II)V
    //   325: aload_0
    //   326: invokespecial 540	com/google/android/gms/internal/zzal:zzU	()V
    //   329: return
    //   330: aload_0
    //   331: bipush 27
    //   333: aload_1
    //   334: aload_0
    //   335: getfield 526	com/google/android/gms/internal/zzal:zznq	Lcom/google/android/gms/internal/zzap;
    //   338: invokestatic 542	com/google/android/gms/internal/zzal:zza	(Landroid/content/Context;Lcom/google/android/gms/internal/zzap;)Ljava/lang/String;
    //   341: invokevirtual 510	com/google/android/gms/internal/zzal:zza	(ILjava/lang/String;)V
    //   344: goto -158 -> 186
    //   347: astore 8
    //   349: goto -155 -> 194
    //   352: astore_2
    //   353: return
    //   354: astore 14
    //   356: goto -31 -> 325
    //   359: astore 13
    //   361: goto -57 -> 304
    //   364: astore 12
    //   366: goto -80 -> 286
    //   369: astore 11
    //   371: goto -102 -> 269
    //   374: astore 10
    //   376: goto -126 -> 250
    //   379: astore 9
    //   381: goto -165 -> 216
    //   384: astore 7
    //   386: goto -212 -> 174
    //   389: astore 6
    //   391: goto -237 -> 154
    //   394: astore 5
    //   396: goto -292 -> 104
    //   399: astore 4
    //   401: goto -350 -> 51
    //   404: astore_3
    //   405: goto -369 -> 36
    // Local variable table:
    //   start	length	slot	name	signature
    //   0	408	0	this	zzal
    //   0	408	1	paramContext	Context
    //   352	1	2	localIOException	IOException
    //   404	1	3	localzza1	zza
    //   399	1	4	localzza2	zza
    //   394	1	5	localzza3	zza
    //   389	1	6	localzza4	zza
    //   384	1	7	localzza5	zza
    //   347	1	8	localzza6	zza
    //   379	1	9	localzza7	zza
    //   374	1	10	localzza8	zza
    //   369	1	11	localzza9	zza
    //   364	1	12	localzza10	zza
    //   359	1	13	localzza11	zza
    //   354	1	14	localzza12	zza
    //   220	16	15	arrayOfInt	int[]
    //   108	24	16	localArrayList	ArrayList
    //   57	22	17	l	long
    // Exception table:
    //   from	to	target	type
    //   174	186	347	com/google/android/gms/internal/zzal$zza
    //   186	194	347	com/google/android/gms/internal/zzal$zza
    //   330	344	347	com/google/android/gms/internal/zzal$zza
    //   0	21	352	java/io/IOException
    //   21	36	352	java/io/IOException
    //   36	51	352	java/io/IOException
    //   51	96	352	java/io/IOException
    //   96	104	352	java/io/IOException
    //   104	154	352	java/io/IOException
    //   154	174	352	java/io/IOException
    //   174	186	352	java/io/IOException
    //   186	194	352	java/io/IOException
    //   194	216	352	java/io/IOException
    //   216	250	352	java/io/IOException
    //   250	269	352	java/io/IOException
    //   269	286	352	java/io/IOException
    //   286	304	352	java/io/IOException
    //   304	325	352	java/io/IOException
    //   325	329	352	java/io/IOException
    //   330	344	352	java/io/IOException
    //   304	325	354	com/google/android/gms/internal/zzal$zza
    //   286	304	359	com/google/android/gms/internal/zzal$zza
    //   269	286	364	com/google/android/gms/internal/zzal$zza
    //   250	269	369	com/google/android/gms/internal/zzal$zza
    //   216	250	374	com/google/android/gms/internal/zzal$zza
    //   194	216	379	com/google/android/gms/internal/zzal$zza
    //   154	174	384	com/google/android/gms/internal/zzal$zza
    //   104	154	389	com/google/android/gms/internal/zzal$zza
    //   51	96	394	com/google/android/gms/internal/zzal$zza
    //   96	104	394	com/google/android/gms/internal/zzal$zza
    //   36	51	399	com/google/android/gms/internal/zzal$zza
    //   21	36	404	com/google/android/gms/internal/zzal$zza
  }
  
  /* Error */
  protected void zzd(Context paramContext)
  {
    // Byte code:
    //   0: aload_0
    //   1: aload_1
    //   2: invokespecial 498	com/google/android/gms/internal/zzal:zze	(Landroid/content/Context;)V
    //   5: getstatic 58	com/google/android/gms/internal/zzal:zznO	Ljava/util/Random;
    //   8: invokevirtual 501	java/util/Random:nextInt	()I
    //   11: putstatic 503	com/google/android/gms/internal/zzal:zznN	I
    //   14: aload_0
    //   15: iconst_2
    //   16: invokestatic 512	com/google/android/gms/internal/zzal:zzV	()Ljava/lang/String;
    //   19: invokevirtual 510	com/google/android/gms/internal/zzal:zza	(ILjava/lang/String;)V
    //   22: aload_0
    //   23: iconst_1
    //   24: invokestatic 507	com/google/android/gms/internal/zzal:zzX	()Ljava/lang/String;
    //   27: invokevirtual 510	com/google/android/gms/internal/zzal:zza	(ILjava/lang/String;)V
    //   30: aload_0
    //   31: bipush 25
    //   33: invokestatic 220	com/google/android/gms/internal/zzal:zzW	()Ljava/lang/Long;
    //   36: invokevirtual 224	java/lang/Long:longValue	()J
    //   39: invokevirtual 515	com/google/android/gms/internal/zzal:zza	(IJ)V
    //   42: iconst_0
    //   43: getstatic 503	com/google/android/gms/internal/zzal:zznN	I
    //   46: invokestatic 505	com/google/android/gms/internal/zzal:zza	(II)V
    //   49: aload_0
    //   50: getfield 547	com/google/android/gms/internal/zzal:zzno	Landroid/view/MotionEvent;
    //   53: aload_0
    //   54: getfield 551	com/google/android/gms/internal/zzal:zznp	Landroid/util/DisplayMetrics;
    //   57: invokestatic 553	com/google/android/gms/internal/zzal:zza	(Landroid/view/MotionEvent;Landroid/util/DisplayMetrics;)Ljava/util/ArrayList;
    //   60: astore 9
    //   62: aload_0
    //   63: bipush 14
    //   65: aload 9
    //   67: iconst_0
    //   68: invokevirtual 520	java/util/ArrayList:get	(I)Ljava/lang/Object;
    //   71: checkcast 139	java/lang/Long
    //   74: invokevirtual 224	java/lang/Long:longValue	()J
    //   77: invokevirtual 515	com/google/android/gms/internal/zzal:zza	(IJ)V
    //   80: aload_0
    //   81: bipush 15
    //   83: aload 9
    //   85: iconst_1
    //   86: invokevirtual 520	java/util/ArrayList:get	(I)Ljava/lang/Object;
    //   89: checkcast 139	java/lang/Long
    //   92: invokevirtual 224	java/lang/Long:longValue	()J
    //   95: invokevirtual 515	com/google/android/gms/internal/zzal:zza	(IJ)V
    //   98: aload 9
    //   100: invokevirtual 307	java/util/ArrayList:size	()I
    //   103: iconst_3
    //   104: if_icmplt +21 -> 125
    //   107: aload_0
    //   108: bipush 16
    //   110: aload 9
    //   112: iconst_2
    //   113: invokevirtual 520	java/util/ArrayList:get	(I)Ljava/lang/Object;
    //   116: checkcast 139	java/lang/Long
    //   119: invokevirtual 224	java/lang/Long:longValue	()J
    //   122: invokevirtual 515	com/google/android/gms/internal/zzal:zza	(IJ)V
    //   125: bipush 14
    //   127: getstatic 503	com/google/android/gms/internal/zzal:zznN	I
    //   130: invokestatic 505	com/google/android/gms/internal/zzal:zza	(II)V
    //   133: aload_0
    //   134: bipush 34
    //   136: aload_1
    //   137: invokestatic 536	com/google/android/gms/internal/zzal:zzg	(Landroid/content/Context;)Ljava/lang/String;
    //   140: invokevirtual 510	com/google/android/gms/internal/zzal:zza	(ILjava/lang/String;)V
    //   143: aload_0
    //   144: bipush 35
    //   146: aload_1
    //   147: invokestatic 538	com/google/android/gms/internal/zzal:zzh	(Landroid/content/Context;)Ljava/lang/Long;
    //   150: invokevirtual 224	java/lang/Long:longValue	()J
    //   153: invokevirtual 515	com/google/android/gms/internal/zzal:zza	(IJ)V
    //   156: aload_0
    //   157: invokespecial 540	com/google/android/gms/internal/zzal:zzU	()V
    //   160: return
    //   161: astore_2
    //   162: return
    //   163: astore 8
    //   165: goto -9 -> 156
    //   168: astore 7
    //   170: goto -27 -> 143
    //   173: astore 6
    //   175: goto -42 -> 133
    //   178: astore 5
    //   180: goto -138 -> 42
    //   183: astore 4
    //   185: goto -155 -> 30
    //   188: astore_3
    //   189: goto -167 -> 22
    // Local variable table:
    //   start	length	slot	name	signature
    //   0	192	0	this	zzal
    //   0	192	1	paramContext	Context
    //   161	1	2	localIOException	IOException
    //   188	1	3	localzza1	zza
    //   183	1	4	localzza2	zza
    //   178	1	5	localzza3	zza
    //   173	1	6	localzza4	zza
    //   168	1	7	localzza5	zza
    //   163	1	8	localzza6	zza
    //   60	51	9	localArrayList	ArrayList
    // Exception table:
    //   from	to	target	type
    //   0	14	161	java/io/IOException
    //   14	22	161	java/io/IOException
    //   22	30	161	java/io/IOException
    //   30	42	161	java/io/IOException
    //   42	49	161	java/io/IOException
    //   49	125	161	java/io/IOException
    //   125	133	161	java/io/IOException
    //   133	143	161	java/io/IOException
    //   143	156	161	java/io/IOException
    //   156	160	161	java/io/IOException
    //   143	156	163	com/google/android/gms/internal/zzal$zza
    //   133	143	168	com/google/android/gms/internal/zzal$zza
    //   49	125	173	com/google/android/gms/internal/zzal$zza
    //   125	133	173	com/google/android/gms/internal/zzal$zza
    //   30	42	178	com/google/android/gms/internal/zzal$zza
    //   22	30	183	com/google/android/gms/internal/zzal$zza
    //   14	22	188	com/google/android/gms/internal/zzal$zza
  }
  
  static class zza
    extends Exception
  {
    public zza() {}
    
    public zza(Throwable paramThrowable)
    {
      super();
    }
  }
}


/* Location:              D:\Apk\dex2jar-0.0.9.15\classes-dex2jar.jar!\com\google\android\gms\internal\zzal.class
 * Java compiler version: 6 (50.0)
 * JD-Core Version:       0.7.1
 */