package com.purplebrain.adbuddiz.sdk.e.a.b;

import com.purplebrain.adbuddiz.sdk.f.a.a;
import com.purplebrain.adbuddiz.sdk.f.a.f;
import java.util.ArrayList;
import java.util.Collection;
import java.util.Iterator;
import java.util.List;

public final class e
  extends c
{
  private void a(f paramf, com.purplebrain.adbuddiz.sdk.f.a.a.c paramc)
  {
    paramf.a(paramc);
    this.a.a(paramf);
  }
  
  /* Error */
  public final void a(com.purplebrain.adbuddiz.sdk.f.a.a.c paramc)
  {
    // Byte code:
    //   0: aload_1
    //   1: getfield 35	com/purplebrain/adbuddiz/sdk/f/a/a/c:b	Lcom/purplebrain/adbuddiz/sdk/f/a/a/d;
    //   4: getstatic 38	com/purplebrain/adbuddiz/sdk/f/a/a/d:b	Lcom/purplebrain/adbuddiz/sdk/f/a/a/d;
    //   7: if_acmpne +17 -> 24
    //   10: aload_0
    //   11: getfield 18	com/purplebrain/adbuddiz/sdk/e/a/b/e:a	Lcom/purplebrain/adbuddiz/sdk/e/a/b/c$a;
    //   14: aload_1
    //   15: getfield 41	com/purplebrain/adbuddiz/sdk/f/a/a/c:a	Lcom/purplebrain/adbuddiz/sdk/f/a/a;
    //   18: invokeinterface 43 2 0
    //   23: return
    //   24: aload_1
    //   25: getfield 41	com/purplebrain/adbuddiz/sdk/f/a/a/c:a	Lcom/purplebrain/adbuddiz/sdk/f/a/a;
    //   28: checkcast 12	com/purplebrain/adbuddiz/sdk/f/a/f
    //   31: astore_2
    //   32: invokestatic 48	com/purplebrain/adbuddiz/sdk/i/a/d:a	()Lcom/purplebrain/adbuddiz/sdk/f/e;
    //   35: astore 8
    //   37: aload_2
    //   38: getstatic 50	com/purplebrain/adbuddiz/sdk/f/a/a/d:a	Lcom/purplebrain/adbuddiz/sdk/f/a/a/d;
    //   41: iconst_1
    //   42: aload 8
    //   44: invokestatic 55	com/purplebrain/adbuddiz/sdk/i/c:a	(Lcom/purplebrain/adbuddiz/sdk/f/a/a;Lcom/purplebrain/adbuddiz/sdk/f/a/a/d;ZLcom/purplebrain/adbuddiz/sdk/f/e;)Ljava/util/List;
    //   47: invokeinterface 61 1 0
    //   52: astore 9
    //   54: aload 9
    //   56: invokeinterface 67 1 0
    //   61: ifeq +170 -> 231
    //   64: aload 9
    //   66: invokeinterface 71 1 0
    //   71: checkcast 31	com/purplebrain/adbuddiz/sdk/f/a/a/c
    //   74: astore 73
    //   76: aload 73
    //   78: invokevirtual 74	com/purplebrain/adbuddiz/sdk/f/a/a/c:e	()Z
    //   81: ifeq -27 -> 54
    //   84: aload 73
    //   86: checkcast 76	com/purplebrain/adbuddiz/sdk/f/a/a/g
    //   89: astore 10
    //   91: goto +1507 -> 1598
    //   94: aload 11
    //   96: aload 11
    //   98: getfield 81	com/purplebrain/adbuddiz/sdk/j/b:b	Lcom/purplebrain/adbuddiz/sdk/j/b/a;
    //   101: getstatic 86	com/purplebrain/adbuddiz/sdk/j/b/a/b:b	I
    //   104: invokevirtual 91	com/purplebrain/adbuddiz/sdk/j/b/a:a	(I)Ljava/util/List;
    //   107: putfield 95	com/purplebrain/adbuddiz/sdk/j/b:c	Ljava/util/List;
    //   110: iconst_1
    //   111: istore 12
    //   113: aload 11
    //   115: getfield 95	com/purplebrain/adbuddiz/sdk/j/b:c	Ljava/util/List;
    //   118: invokeinterface 98 1 0
    //   123: ifne +380 -> 503
    //   126: iload 12
    //   128: iconst_5
    //   129: if_icmpgt +374 -> 503
    //   132: iconst_2
    //   133: anewarray 100	java/lang/Object
    //   136: astore 15
    //   138: aload 15
    //   140: iconst_0
    //   141: iload 12
    //   143: invokestatic 106	java/lang/Integer:valueOf	(I)Ljava/lang/Integer;
    //   146: aastore
    //   147: aload 15
    //   149: iconst_1
    //   150: aload 11
    //   152: getfield 95	com/purplebrain/adbuddiz/sdk/j/b:c	Ljava/util/List;
    //   155: invokeinterface 110 1 0
    //   160: invokestatic 106	java/lang/Integer:valueOf	(I)Ljava/lang/Integer;
    //   163: aastore
    //   164: aload 11
    //   166: getfield 95	com/purplebrain/adbuddiz/sdk/j/b:c	Ljava/util/List;
    //   169: astore 16
    //   171: iconst_0
    //   172: istore 17
    //   174: aload 16
    //   176: invokeinterface 61 1 0
    //   181: astore 18
    //   183: aload 18
    //   185: invokeinterface 67 1 0
    //   190: ifeq +168 -> 358
    //   193: aload 11
    //   195: aload 18
    //   197: invokeinterface 71 1 0
    //   202: checkcast 112	com/purplebrain/adbuddiz/sdk/j/b/a/a
    //   205: invokevirtual 115	com/purplebrain/adbuddiz/sdk/j/b:a	(Lcom/purplebrain/adbuddiz/sdk/j/b/a/a;)Lcom/purplebrain/adbuddiz/sdk/f/a/a/c;
    //   208: invokestatic 118	com/purplebrain/adbuddiz/sdk/e/a/b/e:c	(Lcom/purplebrain/adbuddiz/sdk/f/a/a/c;)Z
    //   211: istore 69
    //   213: iload 69
    //   215: ifeq +1376 -> 1591
    //   218: iload 17
    //   220: iconst_1
    //   221: iadd
    //   222: istore 70
    //   224: iload 70
    //   226: istore 17
    //   228: goto -45 -> 183
    //   231: aconst_null
    //   232: astore 10
    //   234: goto +1364 -> 1598
    //   237: aload 10
    //   239: invokestatic 121	com/purplebrain/adbuddiz/sdk/j/b:a	(Lcom/purplebrain/adbuddiz/sdk/f/a/a/c;)Lcom/purplebrain/adbuddiz/sdk/j/b/a;
    //   242: astore 71
    //   244: aload 71
    //   246: ifnonnull +93 -> 339
    //   249: new 25	com/purplebrain/adbuddiz/sdk/j/a/b
    //   252: dup
    //   253: getstatic 126	com/purplebrain/adbuddiz/sdk/j/a/a:a	Lcom/purplebrain/adbuddiz/sdk/j/a/a;
    //   256: ldc -128
    //   258: invokespecial 131	com/purplebrain/adbuddiz/sdk/j/a/b:<init>	(Lcom/purplebrain/adbuddiz/sdk/j/a/a;Ljava/lang/String;)V
    //   261: athrow
    //   262: astore_3
    //   263: aload_3
    //   264: getfield 133	com/purplebrain/adbuddiz/sdk/j/a/b:b	Ljava/util/List;
    //   267: invokeinterface 61 1 0
    //   272: astore 4
    //   274: aload 4
    //   276: invokeinterface 67 1 0
    //   281: ifeq +1298 -> 1579
    //   284: aload 4
    //   286: invokeinterface 71 1 0
    //   291: checkcast 112	com/purplebrain/adbuddiz/sdk/j/b/a/a
    //   294: astore 5
    //   296: aload_3
    //   297: getfield 134	com/purplebrain/adbuddiz/sdk/j/a/b:a	Lcom/purplebrain/adbuddiz/sdk/j/a/a;
    //   300: astore 6
    //   302: aload 5
    //   304: invokevirtual 137	com/purplebrain/adbuddiz/sdk/j/b/a/a:b	()Ljava/util/List;
    //   307: astore 7
    //   309: new 139	java/lang/StringBuilder
    //   312: dup
    //   313: ldc -115
    //   315: invokespecial 144	java/lang/StringBuilder:<init>	(Ljava/lang/String;)V
    //   318: aload 6
    //   320: getfield 147	com/purplebrain/adbuddiz/sdk/j/a/a:j	I
    //   323: invokevirtual 151	java/lang/StringBuilder:append	(I)Ljava/lang/StringBuilder;
    //   326: invokevirtual 155	java/lang/StringBuilder:toString	()Ljava/lang/String;
    //   329: aload 7
    //   331: aconst_null
    //   332: aconst_null
    //   333: invokestatic 160	com/purplebrain/adbuddiz/sdk/j/e:a	(Ljava/lang/String;Ljava/util/List;Lcom/purplebrain/adbuddiz/sdk/f/a/a/c;Ljava/lang/Integer;)V
    //   336: goto -62 -> 274
    //   339: new 78	com/purplebrain/adbuddiz/sdk/j/b
    //   342: dup
    //   343: aload_2
    //   344: aload 71
    //   346: invokespecial 163	com/purplebrain/adbuddiz/sdk/j/b:<init>	(Lcom/purplebrain/adbuddiz/sdk/f/a/a;Lcom/purplebrain/adbuddiz/sdk/j/b/a;)V
    //   349: astore 72
    //   351: aload 72
    //   353: astore 11
    //   355: goto -261 -> 94
    //   358: iload 17
    //   360: ifne +87 -> 447
    //   363: iconst_1
    //   364: anewarray 100	java/lang/Object
    //   367: iconst_0
    //   368: iload 12
    //   370: invokestatic 106	java/lang/Integer:valueOf	(I)Ljava/lang/Integer;
    //   373: aastore
    //   374: aload 11
    //   376: getfield 95	com/purplebrain/adbuddiz/sdk/j/b:c	Ljava/util/List;
    //   379: invokeinterface 61 1 0
    //   384: astore 66
    //   386: aload 66
    //   388: invokeinterface 67 1 0
    //   393: ifeq +110 -> 503
    //   396: aload 11
    //   398: aload 66
    //   400: invokeinterface 71 1 0
    //   405: checkcast 112	com/purplebrain/adbuddiz/sdk/j/b/a/a
    //   408: invokevirtual 115	com/purplebrain/adbuddiz/sdk/j/b:a	(Lcom/purplebrain/adbuddiz/sdk/j/b/a/a;)Lcom/purplebrain/adbuddiz/sdk/f/a/a/c;
    //   411: astore 67
    //   413: aload_0
    //   414: aload 11
    //   416: getfield 166	com/purplebrain/adbuddiz/sdk/j/b:a	Lcom/purplebrain/adbuddiz/sdk/f/a/f;
    //   419: aload 67
    //   421: invokespecial 168	com/purplebrain/adbuddiz/sdk/e/a/b/e:a	(Lcom/purplebrain/adbuddiz/sdk/f/a/f;Lcom/purplebrain/adbuddiz/sdk/f/a/a/c;)V
    //   424: aload_0
    //   425: aload 67
    //   427: invokevirtual 170	com/purplebrain/adbuddiz/sdk/e/a/b/e:b	(Lcom/purplebrain/adbuddiz/sdk/f/a/a/c;)Z
    //   430: pop
    //   431: goto -45 -> 386
    //   434: astore 14
    //   436: new 25	com/purplebrain/adbuddiz/sdk/j/a/b
    //   439: dup
    //   440: getstatic 173	com/purplebrain/adbuddiz/sdk/j/a/a:d	Lcom/purplebrain/adbuddiz/sdk/j/a/a;
    //   443: invokespecial 176	com/purplebrain/adbuddiz/sdk/j/a/b:<init>	(Lcom/purplebrain/adbuddiz/sdk/j/a/a;)V
    //   446: athrow
    //   447: iload 17
    //   449: aload 11
    //   451: getfield 95	com/purplebrain/adbuddiz/sdk/j/b:c	Ljava/util/List;
    //   454: invokeinterface 110 1 0
    //   459: if_icmpeq +79 -> 538
    //   462: iconst_3
    //   463: anewarray 100	java/lang/Object
    //   466: astore 36
    //   468: aload 36
    //   470: iconst_0
    //   471: iload 12
    //   473: invokestatic 106	java/lang/Integer:valueOf	(I)Ljava/lang/Integer;
    //   476: aastore
    //   477: aload 36
    //   479: iconst_1
    //   480: iload 17
    //   482: invokestatic 106	java/lang/Integer:valueOf	(I)Ljava/lang/Integer;
    //   485: aastore
    //   486: aload 36
    //   488: iconst_2
    //   489: aload 11
    //   491: getfield 95	com/purplebrain/adbuddiz/sdk/j/b:c	Ljava/util/List;
    //   494: invokeinterface 110 1 0
    //   499: invokestatic 106	java/lang/Integer:valueOf	(I)Ljava/lang/Integer;
    //   502: aastore
    //   503: aload 11
    //   505: getfield 95	com/purplebrain/adbuddiz/sdk/j/b:c	Ljava/util/List;
    //   508: invokeinterface 98 1 0
    //   513: ifne +358 -> 871
    //   516: iload 12
    //   518: iconst_5
    //   519: if_icmplt +352 -> 871
    //   522: new 25	com/purplebrain/adbuddiz/sdk/j/a/b
    //   525: dup
    //   526: getstatic 178	com/purplebrain/adbuddiz/sdk/j/a/a:e	Lcom/purplebrain/adbuddiz/sdk/j/a/a;
    //   529: aload 11
    //   531: getfield 95	com/purplebrain/adbuddiz/sdk/j/b:c	Ljava/util/List;
    //   534: invokespecial 181	com/purplebrain/adbuddiz/sdk/j/a/b:<init>	(Lcom/purplebrain/adbuddiz/sdk/j/a/a;Ljava/util/List;)V
    //   537: athrow
    //   538: iconst_1
    //   539: anewarray 100	java/lang/Object
    //   542: iconst_0
    //   543: iload 12
    //   545: invokestatic 106	java/lang/Integer:valueOf	(I)Ljava/lang/Integer;
    //   548: aastore
    //   549: aload 11
    //   551: getfield 95	com/purplebrain/adbuddiz/sdk/j/b:c	Ljava/util/List;
    //   554: invokeinterface 61 1 0
    //   559: astore 19
    //   561: aload 19
    //   563: invokeinterface 67 1 0
    //   568: ifeq +281 -> 849
    //   571: aload 19
    //   573: invokeinterface 71 1 0
    //   578: checkcast 112	com/purplebrain/adbuddiz/sdk/j/b/a/a
    //   581: astore 20
    //   583: aload 11
    //   585: getfield 81	com/purplebrain/adbuddiz/sdk/j/b:b	Lcom/purplebrain/adbuddiz/sdk/j/b/a;
    //   588: astore 21
    //   590: aload 21
    //   592: invokevirtual 183	com/purplebrain/adbuddiz/sdk/j/b/a:a	()Ljava/util/List;
    //   595: aload 20
    //   597: invokeinterface 187 2 0
    //   602: pop
    //   603: aload 11
    //   605: aload 20
    //   607: invokevirtual 115	com/purplebrain/adbuddiz/sdk/j/b:a	(Lcom/purplebrain/adbuddiz/sdk/j/b/a/a;)Lcom/purplebrain/adbuddiz/sdk/f/a/a/c;
    //   610: invokestatic 121	com/purplebrain/adbuddiz/sdk/j/b:a	(Lcom/purplebrain/adbuddiz/sdk/f/a/a/c;)Lcom/purplebrain/adbuddiz/sdk/j/b/a;
    //   613: astore 23
    //   615: aload 23
    //   617: invokevirtual 183	com/purplebrain/adbuddiz/sdk/j/b/a:a	()Ljava/util/List;
    //   620: invokeinterface 61 1 0
    //   625: astore 24
    //   627: aload 24
    //   629: invokeinterface 67 1 0
    //   634: ifeq +196 -> 830
    //   637: aload 24
    //   639: invokeinterface 71 1 0
    //   644: checkcast 112	com/purplebrain/adbuddiz/sdk/j/b/a/a
    //   647: astore 26
    //   649: aload 26
    //   651: invokevirtual 137	com/purplebrain/adbuddiz/sdk/j/b/a/a:b	()Ljava/util/List;
    //   654: aload 20
    //   656: invokevirtual 137	com/purplebrain/adbuddiz/sdk/j/b/a/a:b	()Ljava/util/List;
    //   659: invokeinterface 191 2 0
    //   664: pop
    //   665: aload 26
    //   667: invokevirtual 193	com/purplebrain/adbuddiz/sdk/j/b/a/a:c	()Ljava/util/List;
    //   670: aload 20
    //   672: invokevirtual 193	com/purplebrain/adbuddiz/sdk/j/b/a/a:c	()Ljava/util/List;
    //   675: invokeinterface 191 2 0
    //   680: pop
    //   681: aload 20
    //   683: invokevirtual 195	com/purplebrain/adbuddiz/sdk/j/b/a/a:d	()Ljava/util/List;
    //   686: invokeinterface 61 1 0
    //   691: astore 29
    //   693: aload 29
    //   695: invokeinterface 67 1 0
    //   700: ifeq -73 -> 627
    //   703: aload 29
    //   705: invokeinterface 71 1 0
    //   710: checkcast 197	com/purplebrain/adbuddiz/sdk/j/b/b/b
    //   713: astore 30
    //   715: aload 30
    //   717: invokevirtual 199	com/purplebrain/adbuddiz/sdk/j/b/b/b:a	()I
    //   720: getstatic 203	com/purplebrain/adbuddiz/sdk/j/b/b/c:a	I
    //   723: if_icmpne -30 -> 693
    //   726: aload 30
    //   728: checkcast 205	com/purplebrain/adbuddiz/sdk/j/b/b/e
    //   731: astore 31
    //   733: aload 26
    //   735: getstatic 203	com/purplebrain/adbuddiz/sdk/j/b/b/c:a	I
    //   738: invokevirtual 206	com/purplebrain/adbuddiz/sdk/j/b/a/a:a	(I)Ljava/util/List;
    //   741: invokeinterface 61 1 0
    //   746: astore 32
    //   748: aload 32
    //   750: invokeinterface 67 1 0
    //   755: ifeq -62 -> 693
    //   758: aload 32
    //   760: invokeinterface 71 1 0
    //   765: checkcast 197	com/purplebrain/adbuddiz/sdk/j/b/b/b
    //   768: checkcast 205	com/purplebrain/adbuddiz/sdk/j/b/b/e
    //   771: astore 33
    //   773: aload 33
    //   775: invokevirtual 207	com/purplebrain/adbuddiz/sdk/j/b/b/e:b	()Ljava/util/List;
    //   778: aload 31
    //   780: invokevirtual 207	com/purplebrain/adbuddiz/sdk/j/b/b/e:b	()Ljava/util/List;
    //   783: invokeinterface 191 2 0
    //   788: pop
    //   789: aload 33
    //   791: invokevirtual 209	com/purplebrain/adbuddiz/sdk/j/b/b/e:e	()Ljava/util/List;
    //   794: aload 31
    //   796: invokevirtual 209	com/purplebrain/adbuddiz/sdk/j/b/b/e:e	()Ljava/util/List;
    //   799: invokeinterface 191 2 0
    //   804: pop
    //   805: goto -57 -> 748
    //   808: astore 13
    //   810: ldc -45
    //   812: aload 13
    //   814: invokestatic 216	com/purplebrain/adbuddiz/sdk/i/o:a	(Ljava/lang/String;Ljava/lang/Throwable;)V
    //   817: new 25	com/purplebrain/adbuddiz/sdk/j/a/b
    //   820: dup
    //   821: getstatic 219	com/purplebrain/adbuddiz/sdk/j/a/a:i	Lcom/purplebrain/adbuddiz/sdk/j/a/a;
    //   824: aload 13
    //   826: invokespecial 222	com/purplebrain/adbuddiz/sdk/j/a/b:<init>	(Lcom/purplebrain/adbuddiz/sdk/j/a/a;Ljava/lang/Throwable;)V
    //   829: athrow
    //   830: aload 21
    //   832: invokevirtual 183	com/purplebrain/adbuddiz/sdk/j/b/a:a	()Ljava/util/List;
    //   835: aload 23
    //   837: invokevirtual 183	com/purplebrain/adbuddiz/sdk/j/b/a:a	()Ljava/util/List;
    //   840: invokeinterface 191 2 0
    //   845: pop
    //   846: goto -285 -> 561
    //   849: aload 11
    //   851: aload 11
    //   853: getfield 81	com/purplebrain/adbuddiz/sdk/j/b:b	Lcom/purplebrain/adbuddiz/sdk/j/b/a;
    //   856: getstatic 86	com/purplebrain/adbuddiz/sdk/j/b/a/b:b	I
    //   859: invokevirtual 91	com/purplebrain/adbuddiz/sdk/j/b/a:a	(I)Ljava/util/List;
    //   862: putfield 95	com/purplebrain/adbuddiz/sdk/j/b:c	Ljava/util/List;
    //   865: iinc 12 1
    //   868: goto -755 -> 113
    //   871: aload 11
    //   873: getfield 95	com/purplebrain/adbuddiz/sdk/j/b:c	Ljava/util/List;
    //   876: invokeinterface 98 1 0
    //   881: ifeq -858 -> 23
    //   884: aload 11
    //   886: getfield 81	com/purplebrain/adbuddiz/sdk/j/b:b	Lcom/purplebrain/adbuddiz/sdk/j/b/a;
    //   889: getstatic 223	com/purplebrain/adbuddiz/sdk/j/b/a/b:a	I
    //   892: invokevirtual 91	com/purplebrain/adbuddiz/sdk/j/b/a:a	(I)Ljava/util/List;
    //   895: astore 37
    //   897: aload 37
    //   899: invokeinterface 61 1 0
    //   904: astore 38
    //   906: aload 38
    //   908: invokeinterface 67 1 0
    //   913: ifeq +79 -> 992
    //   916: aload 38
    //   918: invokeinterface 71 1 0
    //   923: checkcast 112	com/purplebrain/adbuddiz/sdk/j/b/a/a
    //   926: astore 39
    //   928: aload 39
    //   930: getstatic 203	com/purplebrain/adbuddiz/sdk/j/b/b/c:a	I
    //   933: invokevirtual 206	com/purplebrain/adbuddiz/sdk/j/b/a/a:a	(I)Ljava/util/List;
    //   936: invokeinterface 98 1 0
    //   941: ifne +668 -> 1609
    //   944: iconst_1
    //   945: istore 40
    //   947: iload 40
    //   949: ifeq -43 -> 906
    //   952: aload 39
    //   954: checkcast 225	com/purplebrain/adbuddiz/sdk/j/b/a/c
    //   957: astore 41
    //   959: aload 41
    //   961: getstatic 203	com/purplebrain/adbuddiz/sdk/j/b/b/c:a	I
    //   964: invokevirtual 226	com/purplebrain/adbuddiz/sdk/j/b/a/c:a	(I)Ljava/util/List;
    //   967: astore 42
    //   969: aload 42
    //   971: invokeinterface 98 1 0
    //   976: ifeq +29 -> 1005
    //   979: new 25	com/purplebrain/adbuddiz/sdk/j/a/b
    //   982: dup
    //   983: getstatic 228	com/purplebrain/adbuddiz/sdk/j/a/a:c	Lcom/purplebrain/adbuddiz/sdk/j/a/a;
    //   986: aload 41
    //   988: invokespecial 231	com/purplebrain/adbuddiz/sdk/j/a/b:<init>	(Lcom/purplebrain/adbuddiz/sdk/j/a/a;Lcom/purplebrain/adbuddiz/sdk/j/b/a/a;)V
    //   991: athrow
    //   992: new 25	com/purplebrain/adbuddiz/sdk/j/a/b
    //   995: dup
    //   996: getstatic 233	com/purplebrain/adbuddiz/sdk/j/a/a:b	Lcom/purplebrain/adbuddiz/sdk/j/a/a;
    //   999: aload 37
    //   1001: invokespecial 181	com/purplebrain/adbuddiz/sdk/j/a/b:<init>	(Lcom/purplebrain/adbuddiz/sdk/j/a/a;Ljava/util/List;)V
    //   1004: athrow
    //   1005: aload 42
    //   1007: iconst_0
    //   1008: invokeinterface 237 2 0
    //   1013: checkcast 205	com/purplebrain/adbuddiz/sdk/j/b/b/e
    //   1016: astore 43
    //   1018: invokestatic 242	com/purplebrain/adbuddiz/sdk/e/b:a	()Lcom/purplebrain/adbuddiz/sdk/e/b;
    //   1021: invokevirtual 245	com/purplebrain/adbuddiz/sdk/e/b:b	()Lcom/purplebrain/adbuddiz/sdk/f/b;
    //   1024: astore 44
    //   1026: invokestatic 251	com/purplebrain/adbuddiz/sdk/AdBuddiz:getContext	()Landroid/content/Context;
    //   1029: invokestatic 257	com/purplebrain/adbuddiz/sdk/i/j:h	(Landroid/content/Context;)Landroid/graphics/Point;
    //   1032: astore 45
    //   1034: invokestatic 251	com/purplebrain/adbuddiz/sdk/AdBuddiz:getContext	()Landroid/content/Context;
    //   1037: invokestatic 262	com/purplebrain/adbuddiz/sdk/i/a/l:b	(Landroid/content/Context;)F
    //   1040: fstore 46
    //   1042: iconst_2
    //   1043: anewarray 100	java/lang/Object
    //   1046: astore 47
    //   1048: aload 47
    //   1050: iconst_0
    //   1051: aload 45
    //   1053: getfield 267	android/graphics/Point:x	I
    //   1056: i2f
    //   1057: fload 46
    //   1059: fdiv
    //   1060: f2i
    //   1061: invokestatic 106	java/lang/Integer:valueOf	(I)Ljava/lang/Integer;
    //   1064: aastore
    //   1065: aload 47
    //   1067: iconst_1
    //   1068: aload 45
    //   1070: getfield 270	android/graphics/Point:y	I
    //   1073: i2f
    //   1074: fload 46
    //   1076: fdiv
    //   1077: f2i
    //   1078: invokestatic 106	java/lang/Integer:valueOf	(I)Ljava/lang/Integer;
    //   1081: aastore
    //   1082: new 272	com/purplebrain/adbuddiz/sdk/j/a
    //   1085: dup
    //   1086: aload 44
    //   1088: getfield 278	com/purplebrain/adbuddiz/sdk/f/b:F	Lcom/purplebrain/adbuddiz/sdk/f/f;
    //   1091: aload 45
    //   1093: getfield 267	android/graphics/Point:x	I
    //   1096: aload 45
    //   1098: getfield 270	android/graphics/Point:y	I
    //   1101: fload 46
    //   1103: invokespecial 281	com/purplebrain/adbuddiz/sdk/j/a:<init>	(Lcom/purplebrain/adbuddiz/sdk/f/f;IIF)V
    //   1106: astore 48
    //   1108: aload 43
    //   1110: invokevirtual 283	com/purplebrain/adbuddiz/sdk/j/b/b/e:h	()Ljava/util/List;
    //   1113: astore 49
    //   1115: new 285	java/util/ArrayList
    //   1118: dup
    //   1119: invokespecial 286	java/util/ArrayList:<init>	()V
    //   1122: astore 50
    //   1124: aload 49
    //   1126: invokeinterface 290 1 0
    //   1131: astore 51
    //   1133: aload 51
    //   1135: invokeinterface 293 1 0
    //   1140: ifeq +70 -> 1210
    //   1143: aload 51
    //   1145: invokeinterface 294 1 0
    //   1150: checkcast 296	com/purplebrain/adbuddiz/sdk/j/b/b/f
    //   1153: astore 63
    //   1155: aload 63
    //   1157: invokevirtual 298	com/purplebrain/adbuddiz/sdk/j/b/b/f:b	()Ljava/lang/String;
    //   1160: aload 48
    //   1162: getfield 300	com/purplebrain/adbuddiz/sdk/j/a:a	Lcom/purplebrain/adbuddiz/sdk/f/f;
    //   1165: getfield 305	com/purplebrain/adbuddiz/sdk/f/f:a	Ljava/lang/String;
    //   1168: invokevirtual 311	java/lang/String:matches	(Ljava/lang/String;)Z
    //   1171: ifeq -38 -> 1133
    //   1174: new 313	com/purplebrain/adbuddiz/sdk/j/a$a
    //   1177: dup
    //   1178: iconst_0
    //   1179: invokespecial 316	com/purplebrain/adbuddiz/sdk/j/a$a:<init>	(B)V
    //   1182: astore 64
    //   1184: aload 64
    //   1186: aload 63
    //   1188: putfield 319	com/purplebrain/adbuddiz/sdk/j/a$a:a	Lcom/purplebrain/adbuddiz/sdk/j/b/b/f;
    //   1191: aload 64
    //   1193: dconst_0
    //   1194: putfield 322	com/purplebrain/adbuddiz/sdk/j/a$a:b	D
    //   1197: aload 50
    //   1199: aload 64
    //   1201: invokeinterface 325 2 0
    //   1206: pop
    //   1207: goto -74 -> 1133
    //   1210: aload 48
    //   1212: aload 50
    //   1214: invokevirtual 328	com/purplebrain/adbuddiz/sdk/j/a:a	(Ljava/util/List;)V
    //   1217: aload 48
    //   1219: aload 50
    //   1221: invokevirtual 330	com/purplebrain/adbuddiz/sdk/j/a:b	(Ljava/util/List;)V
    //   1224: aload 48
    //   1226: aload 50
    //   1228: invokevirtual 332	com/purplebrain/adbuddiz/sdk/j/a:c	(Ljava/util/List;)V
    //   1231: aload 50
    //   1233: invokeinterface 98 1 0
    //   1238: ifeq +16 -> 1254
    //   1241: new 25	com/purplebrain/adbuddiz/sdk/j/a/b
    //   1244: dup
    //   1245: getstatic 335	com/purplebrain/adbuddiz/sdk/j/a/a:g	Lcom/purplebrain/adbuddiz/sdk/j/a/a;
    //   1248: aload 41
    //   1250: invokespecial 231	com/purplebrain/adbuddiz/sdk/j/a/b:<init>	(Lcom/purplebrain/adbuddiz/sdk/j/a/a;Lcom/purplebrain/adbuddiz/sdk/j/b/a/a;)V
    //   1253: athrow
    //   1254: aload 50
    //   1256: new 337	com/purplebrain/adbuddiz/sdk/j/a$1
    //   1259: dup
    //   1260: aload 48
    //   1262: invokespecial 340	com/purplebrain/adbuddiz/sdk/j/a$1:<init>	(Lcom/purplebrain/adbuddiz/sdk/j/a;)V
    //   1265: invokestatic 346	java/util/Collections:sort	(Ljava/util/List;Ljava/util/Comparator;)V
    //   1268: aload 50
    //   1270: iconst_0
    //   1271: invokeinterface 237 2 0
    //   1276: checkcast 313	com/purplebrain/adbuddiz/sdk/j/a$a
    //   1279: getfield 319	com/purplebrain/adbuddiz/sdk/j/a$a:a	Lcom/purplebrain/adbuddiz/sdk/j/b/b/f;
    //   1282: astore 52
    //   1284: iconst_1
    //   1285: anewarray 100	java/lang/Object
    //   1288: iconst_0
    //   1289: aload 52
    //   1291: invokevirtual 298	com/purplebrain/adbuddiz/sdk/j/b/b/f:b	()Ljava/lang/String;
    //   1294: aastore
    //   1295: iconst_2
    //   1296: anewarray 100	java/lang/Object
    //   1299: astore 53
    //   1301: aload 53
    //   1303: iconst_0
    //   1304: aload 52
    //   1306: invokevirtual 349	com/purplebrain/adbuddiz/sdk/j/b/b/f:c	()Ljava/lang/Integer;
    //   1309: aastore
    //   1310: aload 53
    //   1312: iconst_1
    //   1313: aload 52
    //   1315: invokevirtual 351	com/purplebrain/adbuddiz/sdk/j/b/b/f:d	()Ljava/lang/Integer;
    //   1318: aastore
    //   1319: iconst_1
    //   1320: anewarray 100	java/lang/Object
    //   1323: iconst_0
    //   1324: aload 52
    //   1326: invokevirtual 354	com/purplebrain/adbuddiz/sdk/j/b/b/f:a	()Lcom/purplebrain/adbuddiz/sdk/j/b/b/g;
    //   1329: aastore
    //   1330: aload 52
    //   1332: invokevirtual 356	com/purplebrain/adbuddiz/sdk/j/b/b/f:e	()Ljava/lang/Integer;
    //   1335: ifnull +14 -> 1349
    //   1338: iconst_1
    //   1339: anewarray 100	java/lang/Object
    //   1342: iconst_0
    //   1343: aload 52
    //   1345: invokevirtual 356	com/purplebrain/adbuddiz/sdk/j/b/b/f:e	()Ljava/lang/Integer;
    //   1348: aastore
    //   1349: aload 52
    //   1351: ifnonnull +14 -> 1365
    //   1354: new 25	com/purplebrain/adbuddiz/sdk/j/a/b
    //   1357: dup
    //   1358: getstatic 335	com/purplebrain/adbuddiz/sdk/j/a/a:g	Lcom/purplebrain/adbuddiz/sdk/j/a/a;
    //   1361: invokespecial 176	com/purplebrain/adbuddiz/sdk/j/a/b:<init>	(Lcom/purplebrain/adbuddiz/sdk/j/a/a;)V
    //   1364: athrow
    //   1365: aload 52
    //   1367: invokevirtual 354	com/purplebrain/adbuddiz/sdk/j/b/b/f:a	()Lcom/purplebrain/adbuddiz/sdk/j/b/b/g;
    //   1370: astore 54
    //   1372: getstatic 361	com/purplebrain/adbuddiz/sdk/j/b/b/g:b	Lcom/purplebrain/adbuddiz/sdk/j/b/b/g;
    //   1375: astore 55
    //   1377: aload 54
    //   1379: aload 55
    //   1381: if_acmpne +64 -> 1445
    //   1384: new 363	com/purplebrain/adbuddiz/sdk/j/d/c
    //   1387: dup
    //   1388: aload_2
    //   1389: aload 52
    //   1391: new 365	java/net/URL
    //   1394: dup
    //   1395: aload 52
    //   1397: invokevirtual 368	com/purplebrain/adbuddiz/sdk/j/b/b/f:f	()Ljava/lang/String;
    //   1400: invokespecial 369	java/net/URL:<init>	(Ljava/lang/String;)V
    //   1403: invokespecial 372	com/purplebrain/adbuddiz/sdk/j/d/c:<init>	(Lcom/purplebrain/adbuddiz/sdk/f/a/a;Lcom/purplebrain/adbuddiz/sdk/j/b/b/f;Ljava/net/URL;)V
    //   1406: astore 61
    //   1408: aload_0
    //   1409: aload_2
    //   1410: aload 61
    //   1412: invokespecial 168	com/purplebrain/adbuddiz/sdk/e/a/b/e:a	(Lcom/purplebrain/adbuddiz/sdk/f/a/f;Lcom/purplebrain/adbuddiz/sdk/f/a/a/c;)V
    //   1415: aload_0
    //   1416: aload 61
    //   1418: invokevirtual 373	com/purplebrain/adbuddiz/sdk/e/a/b/e:a	(Lcom/purplebrain/adbuddiz/sdk/f/a/a/c;)V
    //   1421: return
    //   1422: astore 62
    //   1424: ldc_w 375
    //   1427: aload 62
    //   1429: invokestatic 216	com/purplebrain/adbuddiz/sdk/i/o:a	(Ljava/lang/String;Ljava/lang/Throwable;)V
    //   1432: new 25	com/purplebrain/adbuddiz/sdk/j/a/b
    //   1435: dup
    //   1436: getstatic 126	com/purplebrain/adbuddiz/sdk/j/a/a:a	Lcom/purplebrain/adbuddiz/sdk/j/a/a;
    //   1439: aload 62
    //   1441: invokespecial 222	com/purplebrain/adbuddiz/sdk/j/a/b:<init>	(Lcom/purplebrain/adbuddiz/sdk/j/a/a;Ljava/lang/Throwable;)V
    //   1444: athrow
    //   1445: aload 52
    //   1447: invokevirtual 354	com/purplebrain/adbuddiz/sdk/j/b/b/f:a	()Lcom/purplebrain/adbuddiz/sdk/j/b/b/g;
    //   1450: astore 56
    //   1452: getstatic 377	com/purplebrain/adbuddiz/sdk/j/b/b/g:a	Lcom/purplebrain/adbuddiz/sdk/j/b/b/g;
    //   1455: astore 57
    //   1457: aload 56
    //   1459: aload 57
    //   1461: if_acmpne +96 -> 1557
    //   1464: new 379	com/purplebrain/adbuddiz/sdk/j/d/b
    //   1467: dup
    //   1468: aload_2
    //   1469: aload 52
    //   1471: new 365	java/net/URL
    //   1474: dup
    //   1475: aload 52
    //   1477: invokevirtual 368	com/purplebrain/adbuddiz/sdk/j/b/b/f:f	()Ljava/lang/String;
    //   1480: invokespecial 369	java/net/URL:<init>	(Ljava/lang/String;)V
    //   1483: invokespecial 380	com/purplebrain/adbuddiz/sdk/j/d/b:<init>	(Lcom/purplebrain/adbuddiz/sdk/f/a/a;Lcom/purplebrain/adbuddiz/sdk/j/b/b/f;Ljava/net/URL;)V
    //   1486: astore 58
    //   1488: aload_0
    //   1489: aload_2
    //   1490: aload 58
    //   1492: invokespecial 168	com/purplebrain/adbuddiz/sdk/e/a/b/e:a	(Lcom/purplebrain/adbuddiz/sdk/f/a/f;Lcom/purplebrain/adbuddiz/sdk/f/a/a/c;)V
    //   1495: aload_0
    //   1496: aload 58
    //   1498: invokevirtual 170	com/purplebrain/adbuddiz/sdk/e/a/b/e:b	(Lcom/purplebrain/adbuddiz/sdk/f/a/a/c;)Z
    //   1501: ifne -1478 -> 23
    //   1504: aload_0
    //   1505: aload 58
    //   1507: invokevirtual 373	com/purplebrain/adbuddiz/sdk/e/a/b/e:a	(Lcom/purplebrain/adbuddiz/sdk/f/a/a/c;)V
    //   1510: return
    //   1511: astore 60
    //   1513: ldc_w 375
    //   1516: aload 60
    //   1518: invokestatic 216	com/purplebrain/adbuddiz/sdk/i/o:a	(Ljava/lang/String;Ljava/lang/Throwable;)V
    //   1521: new 25	com/purplebrain/adbuddiz/sdk/j/a/b
    //   1524: dup
    //   1525: getstatic 126	com/purplebrain/adbuddiz/sdk/j/a/a:a	Lcom/purplebrain/adbuddiz/sdk/j/a/a;
    //   1528: aload 60
    //   1530: invokespecial 222	com/purplebrain/adbuddiz/sdk/j/a/b:<init>	(Lcom/purplebrain/adbuddiz/sdk/j/a/a;Ljava/lang/Throwable;)V
    //   1533: athrow
    //   1534: astore 59
    //   1536: ldc_w 382
    //   1539: aload 59
    //   1541: invokestatic 216	com/purplebrain/adbuddiz/sdk/i/o:a	(Ljava/lang/String;Ljava/lang/Throwable;)V
    //   1544: new 25	com/purplebrain/adbuddiz/sdk/j/a/b
    //   1547: dup
    //   1548: getstatic 219	com/purplebrain/adbuddiz/sdk/j/a/a:i	Lcom/purplebrain/adbuddiz/sdk/j/a/a;
    //   1551: aload 59
    //   1553: invokespecial 222	com/purplebrain/adbuddiz/sdk/j/a/b:<init>	(Lcom/purplebrain/adbuddiz/sdk/j/a/a;Ljava/lang/Throwable;)V
    //   1556: athrow
    //   1557: new 25	com/purplebrain/adbuddiz/sdk/j/a/b
    //   1560: dup
    //   1561: getstatic 126	com/purplebrain/adbuddiz/sdk/j/a/a:a	Lcom/purplebrain/adbuddiz/sdk/j/a/a;
    //   1564: aload 52
    //   1566: getfield 385	com/purplebrain/adbuddiz/sdk/j/b/b/f:a	Lcom/purplebrain/adbuddiz/sdk/j/b/b/b;
    //   1569: getfield 388	com/purplebrain/adbuddiz/sdk/j/b/b/b:a	Lcom/purplebrain/adbuddiz/sdk/j/b/a/a;
    //   1572: ldc_w 390
    //   1575: invokespecial 393	com/purplebrain/adbuddiz/sdk/j/a/b:<init>	(Lcom/purplebrain/adbuddiz/sdk/j/a/a;Lcom/purplebrain/adbuddiz/sdk/j/b/a/a;Ljava/lang/String;)V
    //   1578: athrow
    //   1579: aload_0
    //   1580: getfield 18	com/purplebrain/adbuddiz/sdk/e/a/b/e:a	Lcom/purplebrain/adbuddiz/sdk/e/a/b/c$a;
    //   1583: aload_2
    //   1584: aload_3
    //   1585: invokeinterface 396 3 0
    //   1590: return
    //   1591: iload 17
    //   1593: istore 70
    //   1595: goto -1371 -> 224
    //   1598: aload 10
    //   1600: ifnonnull -1363 -> 237
    //   1603: aconst_null
    //   1604: astore 11
    //   1606: goto -1512 -> 94
    //   1609: iconst_0
    //   1610: istore 40
    //   1612: goto -665 -> 947
    // Local variable table:
    //   start	length	slot	name	signature
    //   0	1615	0	this	e
    //   0	1615	1	paramc	com.purplebrain.adbuddiz.sdk.f.a.a.c
    //   31	1553	2	localf	f
    //   262	1323	3	localb	com.purplebrain.adbuddiz.sdk.j.a.b
    //   272	13	4	localIterator1	Iterator
    //   294	9	5	locala1	com.purplebrain.adbuddiz.sdk.j.b.a.a
    //   300	19	6	locala	com.purplebrain.adbuddiz.sdk.j.a.a
    //   307	23	7	localList1	List
    //   35	8	8	locale	com.purplebrain.adbuddiz.sdk.f.e
    //   52	13	9	localIterator2	Iterator
    //   89	1510	10	localg	com.purplebrain.adbuddiz.sdk.f.a.a.g
    //   94	1511	11	localObject	Object
    //   111	755	12	i	int
    //   808	17	13	localException1	Exception
    //   434	1	14	localMalformedURLException1	java.net.MalformedURLException
    //   136	12	15	arrayOfObject1	Object[]
    //   169	6	16	localList2	List
    //   172	1420	17	j	int
    //   181	15	18	localIterator3	Iterator
    //   559	13	19	localIterator4	Iterator
    //   581	101	20	locala2	com.purplebrain.adbuddiz.sdk.j.b.a.a
    //   588	243	21	locala3	com.purplebrain.adbuddiz.sdk.j.b.a
    //   613	223	23	locala4	com.purplebrain.adbuddiz.sdk.j.b.a
    //   625	13	24	localIterator5	Iterator
    //   647	87	26	locala5	com.purplebrain.adbuddiz.sdk.j.b.a.a
    //   691	13	29	localIterator6	Iterator
    //   713	14	30	localb1	com.purplebrain.adbuddiz.sdk.j.b.b.b
    //   731	64	31	locale1	com.purplebrain.adbuddiz.sdk.j.b.b.e
    //   746	13	32	localIterator7	Iterator
    //   771	19	33	locale2	com.purplebrain.adbuddiz.sdk.j.b.b.e
    //   466	21	36	arrayOfObject2	Object[]
    //   895	105	37	localList3	List
    //   904	13	38	localIterator8	Iterator
    //   926	27	39	locala6	com.purplebrain.adbuddiz.sdk.j.b.a.a
    //   945	666	40	k	int
    //   957	292	41	localc	com.purplebrain.adbuddiz.sdk.j.b.a.c
    //   967	39	42	localList4	List
    //   1016	93	43	locale3	com.purplebrain.adbuddiz.sdk.j.b.b.e
    //   1024	63	44	localb2	com.purplebrain.adbuddiz.sdk.f.b
    //   1032	65	45	localPoint	android.graphics.Point
    //   1040	62	46	f	float
    //   1046	20	47	arrayOfObject3	Object[]
    //   1106	155	48	locala7	com.purplebrain.adbuddiz.sdk.j.a
    //   1113	12	49	localList5	List
    //   1122	147	50	localArrayList	ArrayList
    //   1131	13	51	localListIterator	java.util.ListIterator
    //   1282	283	52	localf1	com.purplebrain.adbuddiz.sdk.j.b.b.f
    //   1299	12	53	arrayOfObject4	Object[]
    //   1370	8	54	localg1	com.purplebrain.adbuddiz.sdk.j.b.b.g
    //   1375	5	55	localg2	com.purplebrain.adbuddiz.sdk.j.b.b.g
    //   1450	8	56	localg3	com.purplebrain.adbuddiz.sdk.j.b.b.g
    //   1455	5	57	localg4	com.purplebrain.adbuddiz.sdk.j.b.b.g
    //   1486	20	58	localb3	com.purplebrain.adbuddiz.sdk.j.d.b
    //   1534	18	59	localException2	Exception
    //   1511	18	60	localMalformedURLException2	java.net.MalformedURLException
    //   1406	11	61	localc1	com.purplebrain.adbuddiz.sdk.j.d.c
    //   1422	18	62	localMalformedURLException3	java.net.MalformedURLException
    //   1153	34	63	localf2	com.purplebrain.adbuddiz.sdk.j.b.b.f
    //   1182	18	64	locala8	com.purplebrain.adbuddiz.sdk.j.a.a
    //   384	15	66	localIterator9	Iterator
    //   411	15	67	localc2	com.purplebrain.adbuddiz.sdk.f.a.a.c
    //   211	3	69	bool	boolean
    //   222	1372	70	m	int
    //   242	103	71	locala9	com.purplebrain.adbuddiz.sdk.j.b.a
    //   349	3	72	localb4	com.purplebrain.adbuddiz.sdk.j.b
    //   74	11	73	localc3	com.purplebrain.adbuddiz.sdk.f.a.a.c
    // Exception table:
    //   from	to	target	type
    //   32	54	262	com/purplebrain/adbuddiz/sdk/j/a/b
    //   54	91	262	com/purplebrain/adbuddiz/sdk/j/a/b
    //   94	110	262	com/purplebrain/adbuddiz/sdk/j/a/b
    //   113	126	262	com/purplebrain/adbuddiz/sdk/j/a/b
    //   132	171	262	com/purplebrain/adbuddiz/sdk/j/a/b
    //   174	183	262	com/purplebrain/adbuddiz/sdk/j/a/b
    //   183	213	262	com/purplebrain/adbuddiz/sdk/j/a/b
    //   237	244	262	com/purplebrain/adbuddiz/sdk/j/a/b
    //   249	262	262	com/purplebrain/adbuddiz/sdk/j/a/b
    //   339	351	262	com/purplebrain/adbuddiz/sdk/j/a/b
    //   363	386	262	com/purplebrain/adbuddiz/sdk/j/a/b
    //   386	431	262	com/purplebrain/adbuddiz/sdk/j/a/b
    //   436	447	262	com/purplebrain/adbuddiz/sdk/j/a/b
    //   447	503	262	com/purplebrain/adbuddiz/sdk/j/a/b
    //   503	516	262	com/purplebrain/adbuddiz/sdk/j/a/b
    //   522	538	262	com/purplebrain/adbuddiz/sdk/j/a/b
    //   538	561	262	com/purplebrain/adbuddiz/sdk/j/a/b
    //   561	627	262	com/purplebrain/adbuddiz/sdk/j/a/b
    //   627	693	262	com/purplebrain/adbuddiz/sdk/j/a/b
    //   693	748	262	com/purplebrain/adbuddiz/sdk/j/a/b
    //   748	805	262	com/purplebrain/adbuddiz/sdk/j/a/b
    //   810	830	262	com/purplebrain/adbuddiz/sdk/j/a/b
    //   830	846	262	com/purplebrain/adbuddiz/sdk/j/a/b
    //   849	865	262	com/purplebrain/adbuddiz/sdk/j/a/b
    //   871	906	262	com/purplebrain/adbuddiz/sdk/j/a/b
    //   906	944	262	com/purplebrain/adbuddiz/sdk/j/a/b
    //   952	992	262	com/purplebrain/adbuddiz/sdk/j/a/b
    //   992	1005	262	com/purplebrain/adbuddiz/sdk/j/a/b
    //   1005	1133	262	com/purplebrain/adbuddiz/sdk/j/a/b
    //   1133	1207	262	com/purplebrain/adbuddiz/sdk/j/a/b
    //   1210	1254	262	com/purplebrain/adbuddiz/sdk/j/a/b
    //   1254	1349	262	com/purplebrain/adbuddiz/sdk/j/a/b
    //   1354	1365	262	com/purplebrain/adbuddiz/sdk/j/a/b
    //   1365	1377	262	com/purplebrain/adbuddiz/sdk/j/a/b
    //   1384	1421	262	com/purplebrain/adbuddiz/sdk/j/a/b
    //   1424	1445	262	com/purplebrain/adbuddiz/sdk/j/a/b
    //   1445	1457	262	com/purplebrain/adbuddiz/sdk/j/a/b
    //   1464	1510	262	com/purplebrain/adbuddiz/sdk/j/a/b
    //   1513	1534	262	com/purplebrain/adbuddiz/sdk/j/a/b
    //   1536	1557	262	com/purplebrain/adbuddiz/sdk/j/a/b
    //   1557	1579	262	com/purplebrain/adbuddiz/sdk/j/a/b
    //   113	126	434	java/net/MalformedURLException
    //   132	171	434	java/net/MalformedURLException
    //   174	183	434	java/net/MalformedURLException
    //   183	213	434	java/net/MalformedURLException
    //   363	386	434	java/net/MalformedURLException
    //   386	431	434	java/net/MalformedURLException
    //   447	503	434	java/net/MalformedURLException
    //   538	561	434	java/net/MalformedURLException
    //   561	627	434	java/net/MalformedURLException
    //   627	693	434	java/net/MalformedURLException
    //   693	748	434	java/net/MalformedURLException
    //   748	805	434	java/net/MalformedURLException
    //   830	846	434	java/net/MalformedURLException
    //   849	865	434	java/net/MalformedURLException
    //   113	126	808	java/lang/Exception
    //   132	171	808	java/lang/Exception
    //   174	183	808	java/lang/Exception
    //   183	213	808	java/lang/Exception
    //   363	386	808	java/lang/Exception
    //   386	431	808	java/lang/Exception
    //   447	503	808	java/lang/Exception
    //   538	561	808	java/lang/Exception
    //   561	627	808	java/lang/Exception
    //   627	693	808	java/lang/Exception
    //   693	748	808	java/lang/Exception
    //   748	805	808	java/lang/Exception
    //   830	846	808	java/lang/Exception
    //   849	865	808	java/lang/Exception
    //   1384	1421	1422	java/net/MalformedURLException
    //   1464	1510	1511	java/net/MalformedURLException
    //   1464	1510	1534	java/lang/Exception
  }
  
  public final void a(a parama)
  {
    com.purplebrain.adbuddiz.sdk.f.e locale = com.purplebrain.adbuddiz.sdk.i.a.d.a();
    com.purplebrain.adbuddiz.sdk.f.a.a.d locald = com.purplebrain.adbuddiz.sdk.f.a.a.d.a;
    ArrayList localArrayList = new ArrayList();
    Iterator localIterator = parama.d().iterator();
    while (localIterator.hasNext())
    {
      com.purplebrain.adbuddiz.sdk.f.a.a.c localc2 = (com.purplebrain.adbuddiz.sdk.f.a.a.c)localIterator.next();
      if ((localc2.b == locald) && (localc2.d == true) && (localc2.c.a(locale)) && (localc2.e())) {
        localArrayList.add(localc2);
      }
    }
    if (!localArrayList.isEmpty()) {}
    for (com.purplebrain.adbuddiz.sdk.f.a.a.c localc1 = (com.purplebrain.adbuddiz.sdk.f.a.a.c)localArrayList.get(0);; localc1 = null)
    {
      a(localc1);
      return;
    }
  }
  
  public final void a(a parama, Collection paramCollection)
  {
    Iterator localIterator = parama.d().iterator();
    while (localIterator.hasNext())
    {
      com.purplebrain.adbuddiz.sdk.f.a.a.c localc = (com.purplebrain.adbuddiz.sdk.f.a.a.c)localIterator.next();
      if (localc.c()) {
        d(localc);
      }
    }
  }
  
  public final boolean a(a parama, com.purplebrain.adbuddiz.sdk.f.e parame)
  {
    com.purplebrain.adbuddiz.sdk.f.a.a.c localc = com.purplebrain.adbuddiz.sdk.i.c.a(parama, com.purplebrain.adbuddiz.sdk.f.a.a.d.b, parame);
    if (localc == null) {
      return false;
    }
    return c(localc);
  }
}


/* Location:              D:\Apk\dex2jar-0.0.9.15\classes-dex2jar.jar!\com\purplebrain\adbuddiz\sdk\e\a\b\e.class
 * Java compiler version: 6 (50.0)
 * JD-Core Version:       0.7.1
 */