package com.google.android.gms.ads.internal.reward.client;

import android.os.Binder;
import android.os.IBinder;
import android.os.IInterface;
import android.os.Parcel;
import android.os.RemoteException;

public abstract interface zzb
  extends IInterface
{
  public abstract void destroy()
    throws RemoteException;
  
  public abstract boolean isLoaded()
    throws RemoteException;
  
  public abstract void pause()
    throws RemoteException;
  
  public abstract void resume()
    throws RemoteException;
  
  public abstract void setUserId(String paramString)
    throws RemoteException;
  
  public abstract void show()
    throws RemoteException;
  
  public abstract void zza(RewardedVideoAdRequestParcel paramRewardedVideoAdRequestParcel)
    throws RemoteException;
  
  public abstract void zza(zzd paramzzd)
    throws RemoteException;
  
  public static abstract class zza
    extends Binder
    implements zzb
  {
    public zza()
    {
      attachInterface(this, "com.google.android.gms.ads.internal.reward.client.IRewardedVideoAd");
    }
    
    public static zzb zzaa(IBinder paramIBinder)
    {
      if (paramIBinder == null) {
        return null;
      }
      IInterface localIInterface = paramIBinder.queryLocalInterface("com.google.android.gms.ads.internal.reward.client.IRewardedVideoAd");
      if ((localIInterface != null) && ((localIInterface instanceof zzb))) {
        return (zzb)localIInterface;
      }
      return new zza(paramIBinder);
    }
    
    public IBinder asBinder()
    {
      return this;
    }
    
    public boolean onTransact(int paramInt1, Parcel paramParcel1, Parcel paramParcel2, int paramInt2)
      throws RemoteException
    {
      switch (paramInt1)
      {
      default: 
        return super.onTransact(paramInt1, paramParcel1, paramParcel2, paramInt2);
      case 1598968902: 
        paramParcel2.writeString("com.google.android.gms.ads.internal.reward.client.IRewardedVideoAd");
        return true;
      case 1: 
        paramParcel1.enforceInterface("com.google.android.gms.ads.internal.reward.client.IRewardedVideoAd");
        if (paramParcel1.readInt() != 0) {}
        for (RewardedVideoAdRequestParcel localRewardedVideoAdRequestParcel = RewardedVideoAdRequestParcel.CREATOR.zzn(paramParcel1);; localRewardedVideoAdRequestParcel = null)
        {
          zza(localRewardedVideoAdRequestParcel);
          paramParcel2.writeNoException();
          return true;
        }
      case 2: 
        paramParcel1.enforceInterface("com.google.android.gms.ads.internal.reward.client.IRewardedVideoAd");
        show();
        paramParcel2.writeNoException();
        return true;
      case 3: 
        paramParcel1.enforceInterface("com.google.android.gms.ads.internal.reward.client.IRewardedVideoAd");
        zza(zzd.zza.zzac(paramParcel1.readStrongBinder()));
        paramParcel2.writeNoException();
        return true;
      case 4: 
        paramParcel1.enforceInterface("com.google.android.gms.ads.internal.reward.client.IRewardedVideoAd");
        setUserId(paramParcel1.readString());
        paramParcel2.writeNoException();
        return true;
      case 5: 
        paramParcel1.enforceInterface("com.google.android.gms.ads.internal.reward.client.IRewardedVideoAd");
        boolean bool = isLoaded();
        paramParcel2.writeNoException();
        if (bool) {}
        for (int i = 1;; i = 0)
        {
          paramParcel2.writeInt(i);
          return true;
        }
      case 6: 
        paramParcel1.enforceInterface("com.google.android.gms.ads.internal.reward.client.IRewardedVideoAd");
        pause();
        paramParcel2.writeNoException();
        return true;
      case 7: 
        paramParcel1.enforceInterface("com.google.android.gms.ads.internal.reward.client.IRewardedVideoAd");
        resume();
        paramParcel2.writeNoException();
        return true;
      }
      paramParcel1.enforceInterface("com.google.android.gms.ads.internal.reward.client.IRewardedVideoAd");
      destroy();
      paramParcel2.writeNoException();
      return true;
    }
    
    private static class zza
      implements zzb
    {
      private IBinder zzoo;
      
      zza(IBinder paramIBinder)
      {
        this.zzoo = paramIBinder;
      }
      
      public IBinder asBinder()
      {
        return this.zzoo;
      }
      
      public void destroy()
        throws RemoteException
      {
        Parcel localParcel1 = Parcel.obtain();
        Parcel localParcel2 = Parcel.obtain();
        try
        {
          localParcel1.writeInterfaceToken("com.google.android.gms.ads.internal.reward.client.IRewardedVideoAd");
          this.zzoo.transact(8, localParcel1, localParcel2, 0);
          localParcel2.readException();
          return;
        }
        finally
        {
          localParcel2.recycle();
          localParcel1.recycle();
        }
      }
      
      public boolean isLoaded()
        throws RemoteException
      {
        Parcel localParcel1 = Parcel.obtain();
        Parcel localParcel2 = Parcel.obtain();
        try
        {
          localParcel1.writeInterfaceToken("com.google.android.gms.ads.internal.reward.client.IRewardedVideoAd");
          this.zzoo.transact(5, localParcel1, localParcel2, 0);
          localParcel2.readException();
          int i = localParcel2.readInt();
          boolean bool = false;
          if (i != 0) {
            bool = true;
          }
          return bool;
        }
        finally
        {
          localParcel2.recycle();
          localParcel1.recycle();
        }
      }
      
      public void pause()
        throws RemoteException
      {
        Parcel localParcel1 = Parcel.obtain();
        Parcel localParcel2 = Parcel.obtain();
        try
        {
          localParcel1.writeInterfaceToken("com.google.android.gms.ads.internal.reward.client.IRewardedVideoAd");
          this.zzoo.transact(6, localParcel1, localParcel2, 0);
          localParcel2.readException();
          return;
        }
        finally
        {
          localParcel2.recycle();
          localParcel1.recycle();
        }
      }
      
      public void resume()
        throws RemoteException
      {
        Parcel localParcel1 = Parcel.obtain();
        Parcel localParcel2 = Parcel.obtain();
        try
        {
          localParcel1.writeInterfaceToken("com.google.android.gms.ads.internal.reward.client.IRewardedVideoAd");
          this.zzoo.transact(7, localParcel1, localParcel2, 0);
          localParcel2.readException();
          return;
        }
        finally
        {
          localParcel2.recycle();
          localParcel1.recycle();
        }
      }
      
      public void setUserId(String paramString)
        throws RemoteException
      {
        Parcel localParcel1 = Parcel.obtain();
        Parcel localParcel2 = Parcel.obtain();
        try
        {
          localParcel1.writeInterfaceToken("com.google.android.gms.ads.internal.reward.client.IRewardedVideoAd");
          localParcel1.writeString(paramString);
          this.zzoo.transact(4, localParcel1, localParcel2, 0);
          localParcel2.readException();
          return;
        }
        finally
        {
          localParcel2.recycle();
          localParcel1.recycle();
        }
      }
      
      public void show()
        throws RemoteException
      {
        Parcel localParcel1 = Parcel.obtain();
        Parcel localParcel2 = Parcel.obtain();
        try
        {
          localParcel1.writeInterfaceToken("com.google.android.gms.ads.internal.reward.client.IRewardedVideoAd");
          this.zzoo.transact(2, localParcel1, localParcel2, 0);
          localParcel2.readException();
          return;
        }
        finally
        {
          localParcel2.recycle();
          localParcel1.recycle();
        }
      }
      
      /* Error */
      public void zza(RewardedVideoAdRequestParcel paramRewardedVideoAdRequestParcel)
        throws RemoteException
      {
        // Byte code:
        //   0: invokestatic 26	android/os/Parcel:obtain	()Landroid/os/Parcel;
        //   3: astore_2
        //   4: invokestatic 26	android/os/Parcel:obtain	()Landroid/os/Parcel;
        //   7: astore_3
        //   8: aload_2
        //   9: ldc 28
        //   11: invokevirtual 32	android/os/Parcel:writeInterfaceToken	(Ljava/lang/String;)V
        //   14: aload_1
        //   15: ifnull +41 -> 56
        //   18: aload_2
        //   19: iconst_1
        //   20: invokevirtual 63	android/os/Parcel:writeInt	(I)V
        //   23: aload_1
        //   24: aload_2
        //   25: iconst_0
        //   26: invokevirtual 69	com/google/android/gms/ads/internal/reward/client/RewardedVideoAdRequestParcel:writeToParcel	(Landroid/os/Parcel;I)V
        //   29: aload_0
        //   30: getfield 15	com/google/android/gms/ads/internal/reward/client/zzb$zza$zza:zzoo	Landroid/os/IBinder;
        //   33: iconst_1
        //   34: aload_2
        //   35: aload_3
        //   36: iconst_0
        //   37: invokeinterface 38 5 0
        //   42: pop
        //   43: aload_3
        //   44: invokevirtual 41	android/os/Parcel:readException	()V
        //   47: aload_3
        //   48: invokevirtual 44	android/os/Parcel:recycle	()V
        //   51: aload_2
        //   52: invokevirtual 44	android/os/Parcel:recycle	()V
        //   55: return
        //   56: aload_2
        //   57: iconst_0
        //   58: invokevirtual 63	android/os/Parcel:writeInt	(I)V
        //   61: goto -32 -> 29
        //   64: astore 4
        //   66: aload_3
        //   67: invokevirtual 44	android/os/Parcel:recycle	()V
        //   70: aload_2
        //   71: invokevirtual 44	android/os/Parcel:recycle	()V
        //   74: aload 4
        //   76: athrow
        // Local variable table:
        //   start	length	slot	name	signature
        //   0	77	0	this	zza
        //   0	77	1	paramRewardedVideoAdRequestParcel	RewardedVideoAdRequestParcel
        //   3	68	2	localParcel1	Parcel
        //   7	60	3	localParcel2	Parcel
        //   64	11	4	localObject	Object
        // Exception table:
        //   from	to	target	type
        //   8	14	64	finally
        //   18	29	64	finally
        //   29	47	64	finally
        //   56	61	64	finally
      }
      
      /* Error */
      public void zza(zzd paramzzd)
        throws RemoteException
      {
        // Byte code:
        //   0: invokestatic 26	android/os/Parcel:obtain	()Landroid/os/Parcel;
        //   3: astore_2
        //   4: invokestatic 26	android/os/Parcel:obtain	()Landroid/os/Parcel;
        //   7: astore_3
        //   8: aload_2
        //   9: ldc 28
        //   11: invokevirtual 32	android/os/Parcel:writeInterfaceToken	(Ljava/lang/String;)V
        //   14: aload_1
        //   15: ifnull +44 -> 59
        //   18: aload_1
        //   19: invokeinterface 74 1 0
        //   24: astore 5
        //   26: aload_2
        //   27: aload 5
        //   29: invokevirtual 77	android/os/Parcel:writeStrongBinder	(Landroid/os/IBinder;)V
        //   32: aload_0
        //   33: getfield 15	com/google/android/gms/ads/internal/reward/client/zzb$zza$zza:zzoo	Landroid/os/IBinder;
        //   36: iconst_3
        //   37: aload_2
        //   38: aload_3
        //   39: iconst_0
        //   40: invokeinterface 38 5 0
        //   45: pop
        //   46: aload_3
        //   47: invokevirtual 41	android/os/Parcel:readException	()V
        //   50: aload_3
        //   51: invokevirtual 44	android/os/Parcel:recycle	()V
        //   54: aload_2
        //   55: invokevirtual 44	android/os/Parcel:recycle	()V
        //   58: return
        //   59: aconst_null
        //   60: astore 5
        //   62: goto -36 -> 26
        //   65: astore 4
        //   67: aload_3
        //   68: invokevirtual 44	android/os/Parcel:recycle	()V
        //   71: aload_2
        //   72: invokevirtual 44	android/os/Parcel:recycle	()V
        //   75: aload 4
        //   77: athrow
        // Local variable table:
        //   start	length	slot	name	signature
        //   0	78	0	this	zza
        //   0	78	1	paramzzd	zzd
        //   3	69	2	localParcel1	Parcel
        //   7	61	3	localParcel2	Parcel
        //   65	11	4	localObject	Object
        //   24	37	5	localIBinder	IBinder
        // Exception table:
        //   from	to	target	type
        //   8	14	65	finally
        //   18	26	65	finally
        //   26	50	65	finally
      }
    }
  }
}


/* Location:              D:\Apk\dex2jar-0.0.9.15\classes-dex2jar.jar!\com\google\android\gms\ads\internal\reward\client\zzb.class
 * Java compiler version: 6 (50.0)
 * JD-Core Version:       0.7.1
 */